Workbook
Name Currency: #REF!
Name Currency: #REF!
Name Currency: #REF!
Name Currency: #REF!
Name Currency: #REF!
Name Currency: #REF!
Name Currency: #REF!
Name Currency: #REF!
Name Currency: #REF!
Name Currency: #REF!
Name Currency: #REF!
Name Currency: #REF!
Name Exchange_Rate: #REF!
Name Exchange_Rate: #REF!
Name Exchange_Rate: #REF!
Name Exchange_Rate: #REF!
Name Exchange_Rate: #REF!
Name Exchange_Rate: #REF!
Name Exchange_Rate: #REF!
Name Exchange_Rate: #REF!
Name Exchange_Rate: #REF!
Name Exchange_Rate: #REF!
Name Exchange_Rate: #REF!
Name Exchange_Rate: #REF!
Name ExchangeRate: #REF!
Name ExchangeRate: #REF!
Name ExchangeRate: #REF!
Name ExchangeRate: #REF!
Name ExchangeRate: #REF!
Name ExchangeRate: #REF!
Name ExchangeRate: #REF!
Name ExchangeRate: #REF!
Name ExchangeRate: #REF!
Name ExchangeRate: #REF!
Name ExchangeRate: #REF!
Name ExchangeRate: #REF!
Name IBM: #REF!
Name IBM: #REF!
Name IBM: #REF!
Name IBM: #REF!
Name IBM: #REF!
Name IBM: #REF!
Name IBM: #REF!
Name IBM: #REF!
Name IBM: #REF!
Name IBM: #REF!
Name IBM: #REF!
Name IBM: #REF!
Name Macro13: #REF!
Name Macro13: #REF!
Name Macro13: #REF!
Name Macro13: #REF!
Name Macro13: #REF!
Name Macro13: #REF!
Name Macro13: #REF!
Name Macro13: #REF!
Name Macro13: #REF!
Name Macro13: #REF!
Name Macro13: #REF!
Name Macro13: #REF!

Sheet AI-Stack Commercial Perpetual
A1: All prices without taxes
A2: AI-Stack Enterprise Perpetual License for Commercial
A3: Part Number | B3: Product | C3: Description | D3: Type | E3: Terms & Conditions | F3: MOQ | G3: List Price (TWD) | H3: List Price (USD) | I3: Price for Distributor (TWD) | J3: Price for Distributor (USD)
A4: AEL-G1112-C-P | B4: AI-Stack Enterprise | C4: AI-Stack Enterprise Perpetual License, 1*GPU-Tier1, 1 year SUMS | D4: AI-Stack Enterprise SW License GPU | E4: (1) (2) (3) | F4: 1 | G4: 300000 | H4: 10800 | I4: =G4*0.5 -> 150000 | J4: =H4*0.5 -> 5400
A5: AEL-D1812-C-P | B5: AI-Stack Enterprise | C5: AI-Stack Enterprise Perpetual License, 1*NODE-Tier1, 1 year SUMS | D5: AI-Stack Enterprise SW License GPU | E5: (1) (2) (3) | F5: 1 | G5: =G4*8*0.8 -> 1920000 | H5: =H4*8*0.8 -> 69120 | I5: =G5*0.5 -> 960000 | J5: =H5*0.5 -> 34560
A6: AEL-G1124-C-P | B6: AI-Stack Enterprise | C6: AI-Stack Enterprise Perpetual License, 1*GPU-Tier1, 2 years SUMS | D6: AI-Stack Enterprise SW License GPU | E6: (1) (2) (3) | F6: 1 | G6: =G4*1.2 -> 360000 | H6: =H4*1.2 -> 12960 | I6: =G6*0.5 -> 180000 | J6: =H6*0.5 -> 6480
A7: AEL-D1824-C-P | B7: AI-Stack Enterprise | C7: AI-Stack Enterprise Perpetual License, 1*NODE-Tier1, 2 years SUMS | D7: AI-Stack Enterprise SW License GPU | E7: (1) (2) (3) | F7: 1 | G7: =G6*8*0.8 -> 2304000 | H7: =H6*8*0.8 -> 82944 | I7: =G7*0.5 -> 1152000 | J7: =H7*0.5 -> 41472
A8: AEL-G1136-C-P | B8: AI-Stack Enterprise | C8: AI-Stack Enterprise Perpetual License, 1*GPU-Tier1, 3 years SUMS | D8: AI-Stack Enterprise SW License GPU | E8: (1) (2) (3) | F8: 1 | G8: =G4*1.4 -> 420000 | H8: =H4*1.4 -> 15120 | I8: =G8*0.5 -> 210000 | J8: =H8*0.5 -> 7560
A9: AEL-D1836-C-P | B9: AI-Stack Enterprise | C9: AI-Stack Enterprise Perpetual License, 1*NODE-Tier1, 3 years SUMS | D9: AI-Stack Enterprise SW License GPU | E9: (1) (2) (3) | F9: 1 | G9: =G8*8*0.8 -> 2688000 | H9: =H8*8*0.8 -> 96768 | I9: =G9*0.5 -> 1344000 | J9: =H9*0.5 -> 48384
A10: AER-G1112-C-P | B10: AI-Stack Enterprise | C10: AI-Stack Enterprise SUMS Renewal, 1*GPU-Tier1, 1 year | D10: AI-Stack Enterprise SUMS GPU | E10: (2) (3) | F10: 1 | G10: =G4*0.2 -> 60000 | H10: =H4*0.2 -> 2160 | I10: =G10*0.5 -> 30000 | J10: =H10*0.5 -> 1080
A11: AER-D1812-C-P | B11: AI-Stack Enterprise | C11: AI-Stack Enterprise SUMS Renewal, 1*NODE-Tier1, 1 year | D11: AI-Stack Enterprise SUMS GPU | E11: (2) (3) | F11: 1 | G11: =G10*8*0.8 -> 384000 | H11: =H10*8*0.8 -> 13824 | I11: =G11*0.5 -> 192000 | J11: =H11*0.5 -> 6912
A12: AEU-G1100-C-P | B12: AI-Stack Enterprise | C12: AI-Stack Express to Enterprise Perpetual License Upgrade for 1*GPU-Tier1 | D12: Express-to-Enterprise Upgrade GPU | E12: (3) (4) | F12: 1 | G12: =(G4-G39)*1.3 -> 130000 | H12: =(H4-H39)*1.3 -> 4680 | I12: =G12*0.5 -> 65000 | J12: =H12*0.5 -> 2340
A13: AEU-D1800-C-P | B13: AI-Stack Enterprise | C13: AI-Stack Express to Enterprise Perpetual License Upgrade for 1*NODE-Tier1 | D13: Express-to-Enterprise Upgrade GPU | E13: (3) (4) | F13: 1 | G13: =G12*8*0.8 -> 832000 | H13: =H12*8*0.8 -> 29952 | I13: =G13*0.5 -> 416000 | J13: =H13*0.5 -> 14976
A15: AEL-G2112-C-P | B15: AI-Stack Enterprise | C15: AI-Stack Enterprise Perpetual License, 1*GPU-Tier2, 1 year SUMS | D15: AI-Stack Enterprise SW License GPU | E15: (1) (2) (3) | F15: 1 | G15: =G4/2 -> 150000 | H15: =H4/2 -> 5400 | I15: =G15*0.5 -> 75000 | J15: =H15*0.5 -> 2700
A16: AEL-D2812-C-P | B16: AI-Stack Enterprise | C16: AI-Stack Enterprise Perpetual License, 1*NODE-Tier2, 1 year SUMS | D16: AI-Stack Enterprise SW License GPU | E16: (1) (2) (3) | F16: 1 | G16: =G15*8*0.8 -> 960000 | H16: =H15*8*0.8 -> 34560 | I16: =G16*0.5 -> 480000 | J16: =H16*0.5 -> 17280
A17: AEL-G2124-C-P | B17: AI-Stack Enterprise | C17: AI-Stack Enterprise Perpetual License, 1*GPU-Tier2, 2 years SUMS | D17: AI-Stack Enterprise SW License GPU | E17: (1) (2) (3) | F17: 1 | G17: =G15*1.2 -> 180000 | H17: =H15*1.2 -> 6480 | I17: =G17*0.5 -> 90000 | J17: =H17*0.5 -> 3240
A18: AEL-D2824-C-P | B18: AI-Stack Enterprise | C18: AI-Stack Enterprise Perpetual License, 1*NODE-Tier2, 2 years SUMS | D18: AI-Stack Enterprise SW License GPU | E18: (1) (2) (3) | F18: 1 | G18: =G17*8*0.8 -> 1152000 | H18: =H17*8*0.8 -> 41472 | I18: =G18*0.5 -> 576000 | J18: =H18*0.5 -> 20736
A19: AEL-G2136-C-P | B19: AI-Stack Enterprise | C19: AI-Stack Enterprise Perpetual License, 1*GPU-Tier2, 3 years SUMS | D19: AI-Stack Enterprise SW License GPU | E19: (1) (2) (3) | F19: 1 | G19: =G15*1.4 -> 210000 | H19: =H15*1.4 -> 7560 | I19: =G19*0.5 -> 105000 | J19: =H19*0.5 -> 3780
A20: AEL-D2836-C-P | B20: AI-Stack Enterprise | C20: AI-Stack Enterprise Perpetual License, 1*NODE-Tier2, 3 years SUMS | D20: AI-Stack Enterprise SW License GPU | E20: (1) (2) (3) | F20: 1 | G20: =G19*8*0.8 -> 1344000 | H20: =H19*8*0.8 -> 48384 | I20: =G20*0.5 -> 672000 | J20: =H20*0.5 -> 24192
A21: AER-G2112-C-P | B21: AI-Stack Enterprise | C21: AI-Stack Enterprise SUMS Renewal, 1*GPU-Tier2, 1 year | D21: AI-Stack Enterprise SUMS GPU | E21: (2) (3) | F21: 1 | G21: =G15*0.2 -> 30000 | H21: =H15*0.2 -> 1080 | I21: =G21*0.5 -> 15000 | J21: =H21*0.5 -> 540
A22: AER-D2812-C-P | B22: AI-Stack Enterprise | C22: AI-Stack Enterprise SUMS Renewal, 1*NODE-Tier2, 1 year | D22: AI-Stack Enterprise SUMS GPU | E22: (2) (3) | F22: 1 | G22: =G21*8*0.8 -> 192000 | H22: =H21*8*0.8 -> 6912 | I22: =G22*0.5 -> 96000 | J22: =H22*0.5 -> 3456
A23: AEU-G2100-C-P | B23: AI-Stack Enterprise | C23: AI-Stack Express to Enterprise Perpetual License Upgrade for 1*GPU-Tier2 | D23: Express-to-Enterprise Upgrade GPU | E23: (3) (4) | F23: 1 | G23: =(G15-G48)*1.3 -> 65000 | H23: =(H15-H48)*1.3 -> 2340 | I23: =G23*0.5 -> 32500 | J23: =H23*0.5 -> 1170
A24: AEU-D2800-C-P | B24: AI-Stack Enterprise | C24: AI-Stack Express to Enterprise Perpetual License Upgrade for 1*NODE-Tier2 | D24: Express-to-Enterprise Upgrade GPU | E24: (3) (4) | F24: 1 | G24: =G23*8*0.8 -> 416000 | H24: =H23*8*0.8 -> 14976 | I24: =G24*0.5 -> 208000 | J24: =H24*0.5 -> 7488
A26: AEL-G3112-C-P | B26: AI-Stack Enterprise | C26: AI-Stack Enterprise Perpetual License, 1*GPU-Tier3, 1 year SUMS | D26: AI-Stack Enterprise SW License GPU | E26: (1) (2) (3) | F26: 1 | G26: =G4/4 -> 75000 | H26: =H4/4 -> 2700 | I26: =G26*0.5 -> 37500 | J26: =H26*0.5 -> 1350
A27: AEL-D3812-C-P | B27: AI-Stack Enterprise | C27: AI-Stack Enterprise Perpetual License, 1*NODE-Tier3, 1 year SUMS | D27: AI-Stack Enterprise SW License GPU | E27: (1) (2) (3) | F27: 1 | G27: =G26*8*0.8 -> 480000 | H27: =H26*8*0.8 -> 17280 | I27: =G27*0.5 -> 240000 | J27: =H27*0.5 -> 8640
A28: AEL-G3124-C-P | B28: AI-Stack Enterprise | C28: AI-Stack Enterprise Perpetual License, 1*GPU-Tier3, 2 years SUMS | D28: AI-Stack Enterprise SW License GPU | E28: (1) (2) (3) | F28: 1 | G28: =G26*1.2 -> 90000 | H28: =H26*1.2 -> 3240 | I28: =G28*0.5 -> 45000 | J28: =H28*0.5 -> 1620
A29: AEL-D3824-C-P | B29: AI-Stack Enterprise | C29: AI-Stack Enterprise Perpetual License, 1*NODE-Tier3, 2 years SUMS | D29: AI-Stack Enterprise SW License GPU | E29: (1) (2) (3) | F29: 1 | G29: =G28*8*0.8 -> 576000 | H29: =H28*8*0.8 -> 20736 | I29: =G29*0.5 -> 288000 | J29: =H29*0.5 -> 10368
A30: AEL-G3136-C-P | B30: AI-Stack Enterprise | C30: AI-Stack Enterprise Perpetual License, 1*GPU-Tier3, 3 years SUMS | D30: AI-Stack Enterprise SW License GPU | E30: (1) (2) (3) | F30: 1 | G30: =G26*1.4 -> 105000 | H30: =H26*1.4 -> 3780 | I30: =G30*0.5 -> 52500 | J30: =H30*0.5 -> 1890
A31: AEL-D3836-C-P | B31: AI-Stack Enterprise | C31: AI-Stack Enterprise Perpetual License, 1*NODE-Tier3, 3 years SUMS | D31: AI-Stack Enterprise SW License GPU | E31: (1) (2) (3) | F31: 1 | G31: =G30*8*0.8 -> 672000 | H31: =H30*8*0.8 -> 24192 | I31: =G31*0.5 -> 336000 | J31: =H31*0.5 -> 12096
A32: AER-G3112-C-P | B32: AI-Stack Enterprise | C32: AI-Stack Enterprise SUMS Renewal, 1*GPU-Tier3, 1 year | D32: AI-Stack Enterprise SUMS GPU | E32: (2) (3) | F32: 1 | G32: =G26*0.2 -> 15000 | H32: =H26*0.2 -> 540 | I32: =G32*0.5 -> 7500 | J32: =H32*0.5 -> 270
A33: AER-D3812-C-P | B33: AI-Stack Enterprise | C33: AI-Stack Enterprise SUMS Renewal, 1*NODE-Tier3, 1 year | D33: AI-Stack Enterprise SUMS GPU | E33: (2) (3) | F33: 1 | G33: =G32*8*0.8 -> 96000 | H33: =H32*8*0.8 -> 3456 | I33: =G33*0.5 -> 48000 | J33: =H33*0.5 -> 1728
A34: AEU-G3100-C-P | B34: AI-Stack Enterprise | C34: AI-Stack Express to Enterprise Perpetual License Upgrade for 1*GPU-Tier3 | D34: Express-to-Enterprise Upgrade GPU | E34: (3) (4) | F34: 1 | G34: =(G26-G59)*1.3 -> 19500 | H34: =(H26-H59)*1.3 -> 702 | I34: =G34*0.5 -> 9750 | J34: =H34*0.5 -> 351
A35: AEU-D3800-C-P | B35: AI-Stack Enterprise | C35: AI-Stack Express to Enterprise Perpetual License Upgrade for 1*NODE-Tier3 | D35: Express-to-Enterprise Upgrade GPU | E35: (3) (4) | F35: 1 | G35: =G34*8*0.8 -> 124800 | H35: =H34*8*0.8 -> 4492.8 | I35: =G35*0.5 -> 62400 | J35: =H35*0.5 -> 2246.4
A37: AI-Stack Express Perpetual License for Commercial
A38: Part Number | B38: Product | C38: Description | D38: Type | E38: Terms & Conditions | F38: MOQ | G38: List Price (TWD) | H38: List Price (USD) | I38: Price for Distributor (TWD) | J38: Price for Distributor (USD)
A39: AXL-G1112-C-P | B39: AI-Stack Express | C39: AI-Stack Express Perpetual License, 1*GPU-Tier1, 1 year SUMS | D39: AI-Stack Express SW License GPU | E39: (1) (2) (3) | F39: 1 | G39: 200000 | H39: 7200 | I39: =G39*0.5 -> 100000 | J39: =H39*0.5 -> 3600
A40: AXL-D1812-C-P | B40: AI-Stack Express | C40: AI-Stack Express Perpetual License, 1*NODE-Tier1, 1 year SUMS | D40: AI-Stack Express SW License GPU | E40: (1) (2) (3) | F40: 1 | G40: =G39*8*0.8 -> 1280000 | H40: =H39*8*0.8 -> 46080 | I40: =G40*0.5 -> 640000 | J40: =H40*0.5 -> 23040
A41: AXL-G1124-C-P | B41: AI-Stack Express | C41: AI-Stack Express Perpetual License, 1*GPU-Tier1, 2 year SUMS | D41: AI-Stack Express SW License GPU | E41: (1) (2) (3) | F41: 1 | G41: =G39*1.2 -> 240000 | H41: =H39*1.2 -> 8640 | I41: =G41*0.5 -> 120000 | J41: =H41*0.5 -> 4320
A42: AXL-D1824-C-P | B42: AI-Stack Express | C42: AI-Stack Express Perpetual License, 1*NODE-Tier1, 2 year SUMS | D42: AI-Stack Express SW License GPU | E42: (1) (2) (3) | F42: 1 | G42: =G41*8*0.8 -> 1536000 | H42: =H41*8*0.8 -> 55296 | I42: =G42*0.5 -> 768000 | J42: =H42*0.5 -> 27648
A43: AXL-G1136-C-P | B43: AI-Stack Express | C43: AI-Stack Express Perpetual License, 1*GPU-Tier1, 3 year SUMS | D43: AI-Stack Express SW License GPU | E43: (1) (2) (3) | F43: 1 | G43: =G39*1.4 -> 280000 | H43: =H39*1.4 -> 10080 | I43: =G43*0.5 -> 140000 | J43: =H43*0.5 -> 5040
A44: AXL-D1836-C-P | B44: AI-Stack Express | C44: AI-Stack Express Perpetual License, 1*NODE-Tier1, 3 year SUMS | D44: AI-Stack Express SW License GPU | E44: (1) (2) (3) | F44: 1 | G44: =G43*8*0.8 -> 1792000 | H44: =H43*8*0.8 -> 64512 | I44: =G44*0.5 -> 896000 | J44: =H44*0.5 -> 32256
A45: AXR-G1112-C-P | B45: AI-Stack Express | C45: AI-Stack Express SUMS Renewal, 1*GPU-Tier1, 1 year | D45: AI-Stack Express SUMS GPU | E45: (2) (3) | F45: 1 | G45: =G39*0.2 -> 40000 | H45: =H39*0.2 -> 1440 | I45: =G45*0.5 -> 20000 | J45: =H45*0.5 -> 720
A46: AXR-D0812-C-P | B46: AI-Stack Express | C46: AI-Stack Express SUMS Renewal, 1*NODE-Tier1, 1 year | D46: AI-Stack Express SUMS GPU | E46: (2) (3) | F46: 1 | G46: =G45*0.8*8 -> 256000 | H46: =H45*0.8*8 -> 9216 | I46: =G46*0.5 -> 128000 | J46: =H46*0.5 -> 4608
I47: =G47*0.5 -> 0 | J47: =H47*0.5 -> 0
A48: AXL-G2112-C-P | B48: AI-Stack Express | C48: AI-Stack Express Perpetual License, 1*GPU-Tier2, 1 year SUMS | D48: AI-Stack Express SW License GPU | E48: (1) (2) (3) | F48: 1 | G48: =G39/2 -> 100000 | H48: =H39/2 -> 3600 | I48: =G48*0.5 -> 50000 | J48: =H48*0.5 -> 1800
A49: AXL-D2812-C-P | B49: AI-Stack Express | C49: AI-Stack Express Perpetual License, 1*NODE-Tier2, 1 year SUMS | D49: AI-Stack Express SW License GPU | E49: (1) (2) (3) | F49: 1 | G49: =G48*8*0.8 -> 640000 | H49: =H48*8*0.8 -> 23040 | I49: =G49*0.5 -> 320000 | J49: =H49*0.5 -> 11520
A50: AXL-G2124-C-P | B50: AI-Stack Express | C50: AI-Stack Express Perpetual License, 1*GPU-Tier2, 2 year SUMS | D50: AI-Stack Express SW License GPU | E50: (1) (2) (3) | F50: 1 | G50: =G48*1.2 -> 120000 | H50: =H48*1.2 -> 4320 | I50: =G50*0.5 -> 60000 | J50: =H50*0.5 -> 2160
A51: AXL-D2824-C-P | B51: AI-Stack Express | C51: AI-Stack Express Perpetual License, 1*NODE-Tier2, 2 year SUMS | D51: AI-Stack Express SW License GPU | E51: (1) (2) (3) | F51: 1 | G51: =G50*8*0.8 -> 768000 | H51: =H50*8*0.8 -> 27648 | I51: =G51*0.5 -> 384000 | J51: =H51*0.5 -> 13824
A52: AXL-G2136-C-P | B52: AI-Stack Express | C52: AI-Stack Express Perpetual License, 1*GPU-Tier2, 3 year SUMS | D52: AI-Stack Express SW License GPU | E52: (1) (2) (3) | F52: 1 | G52: =G48*1.4 -> 140000 | H52: =H48*1.4 -> 5040 | I52: =G52*0.5 -> 70000 | J52: =H52*0.5 -> 2520
A53: AXL-D2836-C-P | B53: AI-Stack Express | C53: AI-Stack Express Perpetual License, 1*NODE-Tier2, 3 year SUMS | D53: AI-Stack Express SW License GPU | E53: (1) (2) (3) | F53: 1 | G53: =G52*8*0.8 -> 896000 | H53: =H52*8*0.8 -> 32256 | I53: =G53*0.5 -> 448000 | J53: =H53*0.5 -> 16128
A54: AXR-G2112-C-P | B54: AI-Stack Express | C54: AI-Stack Express SUMS Renewal, 1*GPU-Tier2, 1 year | D54: AI-Stack Express SUMS GPU | E54: (2) (3) | F54: 1 | G54: =G48*0.2 -> 20000 | H54: =H48*0.2 -> 720 | I54: =G54*0.5 -> 10000 | J54: =H54*0.5 -> 360
A55: AXR-D2812-C-P | B55: AI-Stack Express | C55: AI-Stack Express SUMS Renewal, 1*NODE-Tier2, 1 year | D55: AI-Stack Express SUMS GPU | E55: (2) (3) | F55: 1 | G55: =G54*8*0.8 -> 128000 | H55: =H54*8*0.8 -> 4608 | I55: =G55*0.5 -> 64000 | J55: =H55*0.5 -> 2304
I56: =G56*0.5 -> 0 | J56: =H56*0.5 -> 0
A57: AXL-G3112-C-P | B57: AI-Stack Express | C57: AI-Stack Express Perpetual License, 1*GPU-Tier3, 1 year SUMS | D57: AI-Stack Express SW License GPU | E57: (1) (2) (3) | F57: 1 | G57: =G39/4 -> 50000 | H57: =H39/4 -> 1800 | I57: =G57*0.5 -> 25000 | J57: =H57*0.5 -> 900
A58: AXL-D3812-C-P | B58: AI-Stack Express | C58: AI-Stack Express Perpetual License, 1*NODE-Tier3, 1 year SUMS | D58: AI-Stack Express SW License GPU | E58: (1) (2) (3) | F58: 1 | G58: =G57*8*0.8 -> 320000 | H58: =H57*8*0.8 -> 11520 | I58: =G58*0.5 -> 160000 | J58: =H58*0.5 -> 5760
A59: AXL-G3124-C-P | B59: AI-Stack Express | C59: AI-Stack Express Perpetual License, 1*GPU-Tier3, 2 year SUMS | D59: AI-Stack Express SW License GPU | E59: (1) (2) (3) | F59: 1 | G59: =G57*1.2 -> 60000 | H59: =H57*1.2 -> 2160 | I59: =G59*0.5 -> 30000 | J59: =H59*0.5 -> 1080
A60: AXL-D3824-C-P | B60: AI-Stack Express | C60: AI-Stack Express Perpetual License, 1*NODE-Tier3, 2 year SUMS | D60: AI-Stack Express SW License GPU | E60: (1) (2) (3) | F60: 1 | G60: =G59*8*0.8 -> 384000 | H60: =H59*8*0.8 -> 13824 | I60: =G60*0.5 -> 192000 | J60: =H60*0.5 -> 6912
A61: AXL-G3136-C-P | B61: AI-Stack Express | C61: AI-Stack Express Perpetual License, 1*GPU-Tier3, 3 year SUMS | D61: AI-Stack Express SW License GPU | E61: (1) (2) (3) | F61: 1 | G61: =G57*1.4 -> 70000 | H61: =H57*1.4 -> 2520 | I61: =G61*0.5 -> 35000 | J61: =H61*0.5 -> 1260
A62: AXL-D3836-C-P | B62: AI-Stack Express | C62: AI-Stack Express Perpetual License, 1*NODE-Tier3, 3 year SUMS | D62: AI-Stack Express SW License GPU | E62: (1) (2) (3) | F62: 1 | G62: =G61*8*0.8 -> 448000 | H62: =H61*8*0.8 -> 16128 | I62: =G62*0.5 -> 224000 | J62: =H62*0.5 -> 8064
A63: AXR-G3112-C-P | B63: AI-Stack Express | C63: AI-Stack Express SUMS Renewal, 1*GPU-Tier3, 1 year | D63: AI-Stack Express SUMS GPU | E63: (2) (3) | F63: 1 | G63: =G57*0.2 -> 10000 | H63: =H57*0.2 -> 360 | I63: =G63*0.5 -> 5000 | J63: =H63*0.5 -> 180
A64: AXR-D3812-C-P | B64: AI-Stack Express | C64: AI-Stack Express SUMS Renewal, 1*NODE-Tier3, 1 year | D64: AI-Stack Express SUMS GPU | E64: (2) (3) | F64: 1 | G64: =G63*8*0.8 -> 64000 | H64: =H63*8*0.8 -> 2304 | I64: =G64*0.5 -> 32000 | J64: =H64*0.5 -> 1152
A66: *1 NODE consists of 8 GPUs

Sheet AI-Stack Commercial Subscriptio
A1: All prices without taxes
A2: AI-Stack Enterprise Subscription for Commercial
A3: Part Number | B3: Product | C3: Description | D3: Type | E3: Terms & Conditions | F3: MOQ | G3: List Price (TWD) | H3: List Price (USD) | I3: Price for Distributor (TWD) | J3: Price for Distributor (USD)
A4: AEL-G1112-C-S | B4: AI-Stack Enterprise | C4: AI-Stack Enterprise Subscription, 1*GPU-Tier1, 1 year SUMS | D4: AI-Stack Enterprise SW Subscription GPU | E4: (1) (2) (3) | F4: 1 | G4: 150000 | H4: 5400 | I4: =G4*0.5 -> 75000 | J4: =H4*0.5 -> 2700
A5: AEL-D1812-C-S | B5: AI-Stack Enterprise | C5: AI-Stack Enterprise Subscription, 1*NODE-Tier1, 1 year SUMS | D5: AI-Stack Enterprise SW Subscription GPU | E5: (1) (2) (3) | F5: 1 | G5: =G4*8*0.8 -> 960000 | H5: =H4*8*0.8 -> 34560 | I5: =G5*0.5 -> 480000 | J5: =H5*0.5 -> 17280
A6: AEL-G1124-C-S | B6: AI-Stack Enterprise | C6: AI-Stack Enterprise Subscription, 1*GPU-Tier1, 2 years SUMS | D6: AI-Stack Enterprise SW Subscription GPU | E6: (1) (2) (3) | F6: 1 | G6: =G4*1.2 -> 180000 | H6: =H4*1.2 -> 6480 | I6: =G6*0.5 -> 90000 | J6: =H6*0.5 -> 3240
A7: AEL-D1824-C-S | B7: AI-Stack Enterprise | C7: AI-Stack Enterprise Subscription, 1*NODE-Tier1, 2 years SUMS | D7: AI-Stack Enterprise SW Subscription GPU | E7: (1) (2) (3) | F7: 1 | G7: =G6*8*0.8 -> 1152000 | H7: =H6*8*0.8 -> 41472 | I7: =G7*0.5 -> 576000 | J7: =H7*0.5 -> 20736
A8: AEL-G1136-C-S | B8: AI-Stack Enterprise | C8: AI-Stack Enterprise Subscription, 1*GPU-Tier1, 3 years SUMS | D8: AI-Stack Enterprise SW Subscription GPU | E8: (1) (2) (3) | F8: 1 | G8: =G4*1.4 -> 210000 | H8: =H4*1.4 -> 7560 | I8: =G8*0.5 -> 105000 | J8: =H8*0.5 -> 3780
A9: AEL-D1836-C-S | B9: AI-Stack Enterprise | C9: AI-Stack Enterprise Subscription, 1*NODE-Tier1, 3 years SUMS | D9: AI-Stack Enterprise SW Subscription GPU | E9: (1) (2) (3) | F9: 1 | G9: =G8*8*0.8 -> 1344000 | H9: =H8*8*0.8 -> 48384 | I9: =G9*0.5 -> 672000 | J9: =H9*0.5 -> 24192
A10: AEU-G1100-C-S | B10: AI-Stack Enterprise | C10: AI-Stack Express to Enterprise Subscription Upgrade for 1*GPU-Tier1 | D10: Express-to-Enterprise Upgrade GPU | E10: (3) (4) | F10: 1 | G10: =(G4-G33)*1.3 -> 65000 | H10: =(H4-H33)*1.3 -> 2340 | I10: =G10*0.5 -> 32500 | J10: =H10*0.5 -> 1170
A11: AEU-D1800-C-S | B11: AI-Stack Enterprise | C11: AI-Stack Express to Enterprise Subscription Upgrade for 1*NODE-Tier1 | D11: Express-to-Enterprise Upgrade GPU | E11: (3) (4) | F11: 1 | G11: =G10*8*0.8 -> 416000 | H11: =H10*8*0.8 -> 14976 | I11: =G11*0.5 -> 208000 | J11: =H11*0.5 -> 7488
A13: AEL-G2112-C-S | B13: AI-Stack Enterprise | C13: AI-Stack Enterprise Subscription, 1*GPU-Tier2, 1 year SUMS | D13: AI-Stack Enterprise SW Subscription GPU | E13: (1) (2) (3) | F13: 1 | G13: =G4/2 -> 75000 | H13: =H4/2 -> 2700 | I13: =G13*0.5 -> 37500 | J13: =H13*0.5 -> 1350
A14: AEL-D2812-C-S | B14: AI-Stack Enterprise | C14: AI-Stack Enterprise Subscription, 1*NODE-Tier2, 1 year SUMS | D14: AI-Stack Enterprise SW Subscription GPU | E14: (1) (2) (3) | F14: 1 | G14: =G13*8*0.8 -> 480000 | H14: =H13*8*0.8 -> 17280 | I14: =G14*0.5 -> 240000 | J14: =H14*0.5 -> 8640
A15: AEL-G2124-C-S | B15: AI-Stack Enterprise | C15: AI-Stack Enterprise Subscription, 1*GPU-Tier2, 2 years SUMS | D15: AI-Stack Enterprise SW Subscription GPU | E15: (1) (2) (3) | F15: 1 | G15: =G13*1.2 -> 90000 | H15: =H13*1.2 -> 3240 | I15: =G15*0.5 -> 45000 | J15: =H15*0.5 -> 1620
A16: AEL-D2824-C-S | B16: AI-Stack Enterprise | C16: AI-Stack Enterprise Subscription, 1*NODE-Tier2, 2 years SUMS | D16: AI-Stack Enterprise SW Subscription GPU | E16: (1) (2) (3) | F16: 1 | G16: =G15*8*0.8 -> 576000 | H16: =H15*8*0.8 -> 20736 | I16: =G16*0.5 -> 288000 | J16: =H16*0.5 -> 10368
A17: AEL-G2136-C-S | B17: AI-Stack Enterprise | C17: AI-Stack Enterprise Subscription, 1*GPU-Tier2, 3 years SUMS | D17: AI-Stack Enterprise SW Subscription GPU | E17: (1) (2) (3) | F17: 1 | G17: =G13*1.4 -> 105000 | H17: =H13*1.4 -> 3780 | I17: =G17*0.5 -> 52500 | J17: =H17*0.5 -> 1890
A18: AEL-D2836-C-S | B18: AI-Stack Enterprise | C18: AI-Stack Enterprise Subscription, 1*NODE-Tier2, 3 years SUMS | D18: AI-Stack Enterprise SW Subscription GPU | E18: (1) (2) (3) | F18: 1 | G18: =G17*8*0.8 -> 672000 | H18: =H17*8*0.8 -> 24192 | I18: =G18*0.5 -> 336000 | J18: =H18*0.5 -> 12096
A19: AEU-G2100-C-S | B19: AI-Stack Enterprise | C19: AI-Stack Express to Enterprise Subscription Upgrade for 1*GPU-Tier2 | D19: Express-to-Enterprise Upgrade GPU | E19: (3) (4) | F19: 1 | G19: =(G13-G40)*1.3 -> 32500 | H19: =(H13-H40)*1.3 -> 1170 | I19: =G19*0.5 -> 16250 | J19: =H19*0.5 -> 585
A20: AEU-D2800-C-S | B20: AI-Stack Enterprise | C20: AI-Stack Express to Enterprise Subscription Upgrade for 1*NODE-Tier2 | D20: Express-to-Enterprise Upgrade GPU | E20: (3) (4) | F20: 1 | G20: =G19*8*0.8 -> 208000 | H20: =H19*8*0.8 -> 7488 | I20: =G20*0.5 -> 104000 | J20: =H20*0.5 -> 3744
A22: AEL-G3112-C-S | B22: AI-Stack Enterprise | C22: AI-Stack Enterprise Subscription, 1*GPU-Tier3, 1 year SUMS | D22: AI-Stack Enterprise SW Subscription GPU | E22: (1) (2) (3) | F22: 1 | G22: =G4/4 -> 37500 | H22: =H4/4 -> 1350 | I22: =G22*0.5 -> 18750 | J22: =H22*0.5 -> 675
A23: AEL-D3812-C-S | B23: AI-Stack Enterprise | C23: AI-Stack Enterprise Subscription, 1*NODE-Tier3, 1 year SUMS | D23: AI-Stack Enterprise SW Subscription GPU | E23: (1) (2) (3) | F23: 1 | G23: =G22*8*0.8 -> 240000 | H23: =H22*8*0.8 -> 8640 | I23: =G23*0.5 -> 120000 | J23: =H23*0.5 -> 4320
A24: AEL-G3124-C-S | B24: AI-Stack Enterprise | C24: AI-Stack Enterprise Subscription, 1*GPU-Tier3, 2 years SUMS | D24: AI-Stack Enterprise SW Subscription GPU | E24: (1) (2) (3) | F24: 1 | G24: =G22*1.2 -> 45000 | H24: =H22*1.2 -> 1620 | I24: =G24*0.5 -> 22500 | J24: =H24*0.5 -> 810
A25: AEL-D3824-C-S | B25: AI-Stack Enterprise | C25: AI-Stack Enterprise Subscription, 1*NODE-Tier3, 2 years SUMS | D25: AI-Stack Enterprise SW Subscription GPU | E25: (1) (2) (3) | F25: 1 | G25: =G24*8*0.8 -> 288000 | H25: =H24*8*0.8 -> 10368 | I25: =G25*0.5 -> 144000 | J25: =H25*0.5 -> 5184
A26: AEL-G3136-C-S | B26: AI-Stack Enterprise | C26: AI-Stack Enterprise Subscription, 1*GPU-Tier3, 3 years SUMS | D26: AI-Stack Enterprise SW Subscription GPU | E26: (1) (2) (3) | F26: 1 | G26: =G22*1.4 -> 52500 | H26: =H22*1.4 -> 1890 | I26: =G26*0.5 -> 26250 | J26: =H26*0.5 -> 945
A27: AEL-D3836-C-S | B27: AI-Stack Enterprise | C27: AI-Stack Enterprise Subscription, 1*NODE-Tier3, 3 years SUMS | D27: AI-Stack Enterprise SW Subscription GPU | E27: (1) (2) (3) | F27: 1 | G27: =G26*8*0.8 -> 336000 | H27: =H26*8*0.8 -> 12096 | I27: =G27*0.5 -> 168000 | J27: =H27*0.5 -> 6048
A28: AEU-G3100-C-S | B28: AI-Stack Enterprise | C28: AI-Stack Express to Enterprise Subscription Upgrade for 1*GPU-Tier3 | D28: Express-to-Enterprise Upgrade GPU | E28: (3) (4) | F28: 1 | G28: =(G22-G49)*1.3 -> 9750 | H28: =(H22-H49)*1.3 -> 351 | I28: =G28*0.5 -> 4875 | J28: =H28*0.5 -> 175.5
A29: AEU-D3800-C-S | B29: AI-Stack Enterprise | C29: AI-Stack Express to Enterprise Subscription Upgrade for 1*NODE-Tier3 | D29: Express-to-Enterprise Upgrade GPU | E29: (3) (4) | F29: 1 | G29: =G28*8*0.8 -> 62400 | H29: =H28*8*0.8 -> 2246.4 | I29: =G29*0.5 -> 31200 | J29: =H29*0.5 -> 1123.2
A31: AI-Stack Express Subscription for Commercial
A32: Part Number | B32: Product | C32: Description | D32: Type | E32: Terms & Conditions | F32: MOQ | G32: List Price (TWD) | H32: List Price (USD) | I32: Price for Distributor (TWD) | J32: Price for Distributor (USD)
A33: AXL-G1112-C-S | B33: AI-Stack Express | C33: AI-Stack Express Subscription, 1*GPU-Tier1, 1 year SUMS | D33: AI-Stack Express SW Subscription GPU | E33: (1) (2) (3) | F33: 1 | G33: 100000 | H33: 3600 | I33: =G33*0.5 -> 50000 | J33: =H33*0.5 -> 1800
A34: AXL-D1812-C-S | B34: AI-Stack Express | C34: AI-Stack Express Subscription, 1*NODE-Tier1, 1 year SUMS | D34: AI-Stack Express SW Subscription GPU | E34: (1) (2) (3) | F34: 1 | G34: =G33*8*0.8 -> 640000 | H34: =H33*8*0.8 -> 23040 | I34: =G34*0.5 -> 320000 | J34: =H34*0.5 -> 11520
A35: AXL-G1124-C-S | B35: AI-Stack Express | C35: AI-Stack Express Subscription, 1*GPU-Tier1, 2 year SUMS | D35: AI-Stack Express SW Subscription GPU | E35: (1) (2) (3) | F35: 1 | G35: =G33*1.2 -> 120000 | H35: =H33*1.2 -> 4320 | I35: =G35*0.5 -> 60000 | J35: =H35*0.5 -> 2160
A36: AXL-D1824-C-S | B36: AI-Stack Express | C36: AI-Stack Express Subscription, 1*NODE-Tier1, 2 year SUMS | D36: AI-Stack Express SW Subscription GPU | E36: (1) (2) (3) | F36: 1 | G36: =G35*8*0.8 -> 768000 | H36: =H35*8*0.8 -> 27648 | I36: =G36*0.5 -> 384000 | J36: =H36*0.5 -> 13824
A37: AXL-G1136-C-S | B37: AI-Stack Express | C37: AI-Stack Express Subscription, 1*GPU-Tier1, 3 year SUMS | D37: AI-Stack Express SW Subscription GPU | E37: (1) (2) (3) | F37: 1 | G37: =G33*1.4 -> 140000 | H37: =H33*1.4 -> 5040 | I37: =G37*0.5 -> 70000 | J37: =H37*0.5 -> 2520
A38: AXL-D1836-C-S | B38: AI-Stack Express | C38: AI-Stack Express Subscription, 1*NODE-Tier1, 3 year SUMS | D38: AI-Stack Express SW Subscription GPU | E38: (1) (2) (3) | F38: 1 | G38: =G37*8*0.8 -> 896000 | H38: =H37*8*0.8 -> 32256 | I38: =G38*0.5 -> 448000 | J38: =H38*0.5 -> 16128
I39: =G39*0.5 -> 0 | J39: =H39*0.5 -> 0
A40: AXL-G2112-C-S | B40: AI-Stack Express | C40: AI-Stack Express Subscription, 1*GPU-Tier2, 1 year SUMS | D40: AI-Stack Express SW Subscription GPU | E40: (1) (2) (3) | F40: 1 | G40: =G33/2 -> 50000 | H40: =H33/2 -> 1800 | I40: =G40*0.5 -> 25000 | J40: =H40*0.5 -> 900
A41: AXL-D2812-C-S | B41: AI-Stack Express | C41: AI-Stack Express Subscription, 1*NODE-Tier2, 1 year SUMS | D41: AI-Stack Express SW Subscription GPU | E41: (1) (2) (3) | F41: 1 | G41: =G40*8*0.8 -> 320000 | H41: =H40*8*0.8 -> 11520 | I41: =G41*0.5 -> 160000 | J41: =H41*0.5 -> 5760
A42: AXL-G2124-C-S | B42: AI-Stack Express | C42: AI-Stack Express Subscription, 1*GPU-Tier2, 2 year SUMS | D42: AI-Stack Express SW Subscription GPU | E42: (1) (2) (3) | F42: 1 | G42: =G40*1.2 -> 60000 | H42: =H40*1.2 -> 2160 | I42: =G42*0.5 -> 30000 | J42: =H42*0.5 -> 1080
A43: AXL-D2824-C-S | B43: AI-Stack Express | C43: AI-Stack Express Subscription, 1*NODE-Tier2, 2 year SUMS | D43: AI-Stack Express SW Subscription GPU | E43: (1) (2) (3) | F43: 1 | G43: =G42*8*0.8 -> 384000 | H43: =H42*8*0.8 -> 13824 | I43: =G43*0.5 -> 192000 | J43: =H43*0.5 -> 6912
A44: AXL-G2136-C-S | B44: AI-Stack Express | C44: AI-Stack Express Subscription, 1*GPU-Tier2, 3 year SUMS | D44: AI-Stack Express SW Subscription GPU | E44: (1) (2) (3) | F44: 1 | G44: =G40*1.4 -> 70000 | H44: =H40*1.4 -> 2520 | I44: =G44*0.5 -> 35000 | J44: =H44*0.5 -> 1260
A45: AXL-D2836-C-S | B45: AI-Stack Express | C45: AI-Stack Express Subscription, 1*NODE-Tier2, 3 year SUMS | D45: AI-Stack Express SW Subscription GPU | E45: (1) (2) (3) | F45: 1 | G45: =G44*8*0.8 -> 448000 | H45: =H44*8*0.8 -> 16128 | I45: =G45*0.5 -> 224000 | J45: =H45*0.5 -> 8064
I46: =G46*0.5 -> 0 | J46: =H46*0.5 -> 0
A47: AXL-G3112-C-S | B47: AI-Stack Express | C47: AI-Stack Express Subscription, 1*GPU-Tier3, 1 year SUMS | D47: AI-Stack Express SW Subscription GPU | E47: (1) (2) (3) | F47: 1 | G47: =G33/4 -> 25000 | H47: =H33/4 -> 900 | I47: =G47*0.5 -> 12500 | J47: =H47*0.5 -> 450
A48: AXL-D3812-C-S | B48: AI-Stack Express | C48: AI-Stack Express Subscription, 1*NODE-Tier3, 1 year SUMS | D48: AI-Stack Express SW Subscription GPU | E48: (1) (2) (3) | F48: 1 | G48: =G47*8*0.8 -> 160000 | H48: =H47*8*0.8 -> 5760 | I48: =G48*0.5 -> 80000 | J48: =H48*0.5 -> 2880
A49: AXL-G3124-C-S | B49: AI-Stack Express | C49: AI-Stack Express Subscription, 1*GPU-Tier3, 2 year SUMS | D49: AI-Stack Express SW Subscription GPU | E49: (1) (2) (3) | F49: 1 | G49: =G47*1.2 -> 30000 | H49: =H47*1.2 -> 1080 | I49: =G49*0.5 -> 15000 | J49: =H49*0.5 -> 540
A50: AXL-D3824-C-S | B50: AI-Stack Express | C50: AI-Stack Express Subscription, 1*NODE-Tier3, 2 year SUMS | D50: AI-Stack Express SW Subscription GPU | E50: (1) (2) (3) | F50: 1 | G50: =G49*8*0.8 -> 192000 | H50: =H49*8*0.8 -> 6912 | I50: =G50*0.5 -> 96000 | J50: =H50*0.5 -> 3456
A51: AXL-G3136-C-S | B51: AI-Stack Express | C51: AI-Stack Express Subscription, 1*GPU-Tier3, 3 year SUMS | D51: AI-Stack Express SW Subscription GPU | E51: (1) (2) (3) | F51: 1 | G51: =G47*1.4 -> 35000 | H51: =H47*1.4 -> 1260 | I51: =G51*0.5 -> 17500 | J51: =H51*0.5 -> 630
A52: AXL-D3836-C-S | B52: AI-Stack Express | C52: AI-Stack Express Subscription, 1*NODE-Tier3, 3 year SUMS | D52: AI-Stack Express SW Subscription GPU | E52: (1) (2) (3) | F52: 1 | G52: =G51*8*0.8 -> 224000 | H52: =H51*8*0.8 -> 8064 | I52: =G52*0.5 -> 112000 | J52: =H52*0.5 -> 4032
A54: *1 NODE consists of 8 GPUs

Sheet DGX-1
C1: NVPN | D1: Type (10%off) | E1: 牌價 | F1: Zerone price (牌價*0.95*0.95) | G1: COGS(+160) | H1: FOB (5% margin) | I1: TWD(*33) | J1: Leadtek Partner Price | K1: Suggested End User Price
A2: Standard | B2: Standard | C2: 920-22787-2500-000 | D2: 8-GPU/512GB DGX-1 Deep Learning System with P100 | E2: 129000 | F2: 116422.5 | G2: =F2+160 -> 116582.5 | H2: =G2/0.95 -> 122718.42 | I2: =H2*33 -> 4049707.9 | J2: 3837000 | K2: 4265000
B3: Standard | C3: 930-22787-2510-0U1 | D3: Upgrade kit for DGX-1 DL System with P100 to V100 | E3: 20000 | F3: 18050 | G3: NA | H3: =F3/0.95 -> 19000 | I3: =H3*33 -> 627000 | J3: 575000 | K3: 639000
B4: Standard | C4: 718-22787-2510-001 | D4: 8GPU/512GB DGX-1 DL System V100 1yr Support | E4: 22350 | F4: 20170.88 | G4: NA | H4: =F4/0.95 -> 21232.505 | I4: =H4*33 -> 700672.67 | J4: 1638000 | K4: 1820000
B5: Standard | C5: 718-22787-2510-003 | D5: 8GPU/512GB DGX-1 DL System V100 3yr Support | E5: 63698 | F5: 57487.45
B6: EDU 30%0ff Program | C6: 920-22787-2500-000 | D6: 8-GPU/512GB DGX-1 Deep Learning System with P100 | E6: 90300 | F6: 81495.75 | G6: =F6+160 -> 81655.75 | H6: =F6/0.95 -> 85785 | I6: =H6*33 -> 2830905 | J6: 2687500 | K6: 2985500
B7: EDU 30%0ff Program | C7: 930-22787-2510-0U1 | D7: Upgrade Kit for DGX-1 DL System with P100 to V100 | E7: 20000 | F7: 18050 | G7: NA | H7: =F7/0.95 -> 19000 | I7: =H7*33 -> 627000 | J7: 402300 | K7: 447300
B8: EDU 30%0ff Program | C8: 718-22787-2510-ED1 | D8: 8GPU/512GB DGX-1 DL System V100 1yr Sup EDU | E8: 15645 | F8: 14119.62 | G8: NA | H8: =F8/0.95 -> 14862.758 | I8: =H8*33 -> 490471.01 | J8: 1146550 | K8: 1274000
B9: EDU 30%0ff Program | C9: 718-22787-2510-ED3 | D9: 8GPU/512GB DGX-1 DL System V100 3yr Sup EDU | E9: 44589 | F9: 40241.57 | G9: NA | H9: =F9/0.95 -> 42359.547 | I9: =H9*33 -> 1397865.1 | J9: 1146550 | K9: 1274000
A10: NPN 擎昊/鴻鵠 | B10: Standard (extra 10%off) | C10: 920-22787-2500-000 | D10: 8-GPU/512GB DGX-1 Deep Learning System with P100 | E10: 129000 | F10: 98040 | G10: =F10+160 -> 98200 | H10: =G10/0.95 -> 103368.42 | I10: =H10*33 -> 3411157.9 | J10: 3453800 | K10: 4265000
B11: Standard (extra 10%off) | C11: 930-22787-2510-0U1 | D11: Upgrade kit for DGX-1 DL System with P100 to V100 | E11: 20000 | F11: 15200 | G11: NA | H11: =F11/0.95 -> 16000 | I11: =H11*33 -> 528000 | J11: 517500 | K11: 639000
B12: Standard (extra 10%off) | C12: 718-22787-2510-001 | D12: 8GPU/512GB DGX-1 DL System V100 1yr Support | E12: 22350 | F12: 16986 | G12: NA | H12: =F12/0.95 -> 17880 | I12: =H12*33 -> 590040 | J12: 1474200 | K12: 1820000
B13: Standard (extra 10%off) | C13: 718-22787-2510-003 | D13: 8GPU/512GB DGX-1 DL System V100 3yr Support | E13: 63698 | F13: 48410.48 | H13: =F13/0.95 -> 50958.4 | I13: =H13*33 -> 1681627.2
B14: EDU 30%0ff Program (extra 10%off) | C14: 920-22787-2500-000 | D14: 8-GPU/512GB DGX-1 Deep Learning System with P100 | E14: 90300 | F14: 68628 | G14: =F14+160 -> 68788 | H14: =G14/0.95 -> 72408.421 | I14: =H14*33 -> 2389477.9 | J14: 2419300 | K14: 2985500
B15: EDU 30%0ff Program (extra 10%off) | C15: 930-22787-2510-0U1 | D15: Upgrade Kit for DGX-1 DL System with P100 to V100 | E15: 20000 | F15: 10640 | G15: NA | H15: =F15/0.95 -> 11200 | I15: =H15*33 -> 369600 | J15: 362100 | K15: 447300
B16: EDU 30%0ff Program (extra 10%off) | C16: 718-22787-2510-ED1 | D16: 8GPU/512GB DGX-1 DL System V100 1yr Sup EDU | E16: 15645 | F16: 11890 | G16: NA | H16: =F16/0.95 -> 12515.789 | I16: =H16*33 -> 413021.05 | J16: 1031900 | K16: 1274000
B17: Start-up | C17: 920-22787-2500-000 | D17: DGX-1 Hardware | F17: =F2*0.7 -> 81495.75 | G17: =F17+160 -> 81655.75 | H17: =G17/0.95 -> 85953.421 | I17: =H17*33 -> 2836462.9 | J17: 2687500 | K17: 2985500
B18: Start-up | C18: 718-22787-2500-001 | D18: DGX-1 1 Yr Support | F18: =F3*0.7 -> 12635 | G18: NA | H18: =F18/0.95 -> 13300 | I18: =H18*33 -> 438900 | J18: 402300 | K18: 447300
B19: Start-up | C19: 718-22787-2500-003 | D19: DGX-1 3 Yr Support | F19: =F4*0.7 -> 14119.616 | G19: NA | H19: =F19/0.95 -> 14862.754 | I19: =H19*33 -> 490470.87 | J19: 1146550 | K19: 1274000

Sheet AI-Stack Commercial Service
A1: All prices without taxes
A2: AI-Stack Professional Service for Commercial
A3: Part Number | B3: Product | C3: Description | D3: Type | E3: MOQ | F3: List Price (TWD) | G3: List Price (USD) | H3: Price for Distributor (TWD) | I3: Price for Distributor (USD)
A4: APS-C10001-C | B4: AI-Stack Professional Service | C4: AI-Stack Consultant Service, 1*Day | D4: AI-Stack Consultant Service | E4: 1 | F4: 45000 | G4: 1620 | H4: =F4*0.8 -> 36000 | I4: =G4*0.8 -> 1296
A5: APS-C05001-C | B5: AI-Stack Professional Service | C5: AI-Stack Consultant Service, 0.5*Day | D5: AI-Stack Consultant Service | E5: 1 | F5: 25000 | G5: 900 | H5: =F5*0.8 -> 20000 | I5: =G5*0.8 -> 720
A6: APS-T10001-C | B6: AI-Stack Professional Service | C6: AI-Stack Training Service, 1*Day | D6: AI-Stack Training Service | E6: 1 | F6: 30000 | G6: 1080 | H6: =F6*0.8 -> 24000 | I6: =G6*0.8 -> 864
A7: APS-T10001-C | B7: AI-Stack Professional Service | C7: AI-Stack Training Service, 0.5*Day | D7: AI-Stack Training Service | E7: 1 | F7: 17500 | G7: 630 | H7: =F7*0.8 -> 14000 | I7: =G7*0.8 -> 504

Sheet AI-Stack Education Perpetual
A1: 教育版支援的單位及範圍(規則)
A2: 數位無限教育版軟體優惠授權及其相關的軟體保固(MA/SUMS) ，僅售予教育部全球資訊網所認定之各級學校及合格之非盈利教育機構 ，及中央或地方政府教育主管機關為提供各級學校使用之統籌計劃，用於非屬營利目的之教學、研究、及其他支持教育目的相關之師生與教職人員之使用，不得另行轉售。任何商業或以營利為目的之用途均不得安裝與使用。
A3: All prices without taxes
A4: AI-Stack Enterprise Perpetual License for Education
A5: Part Number | B5: Product | C5: Description | D5: Type | E5: Terms & Conditions | F5: MOQ | G5: List Price (TWD) | H5: List Price (USD) | I5: Price for Distributor (TWD) | J5: Price for Distributor (USD)
A6: AEL-G1112-E-P | B6: AI-Stack Enterprise EDU | C6: AI-Stack Enterprise EDU Perpetual License, 1*GPU-Tier1, 1 year SUMS | D6: AI-Stack Enterprise SW License GPU | E6: (1) (2) (3) | F6: 1 | G6: ='AI-Stack Commercial Perpetual'!G4*0.8 -> 240000 | H6: ='AI-Stack Commercial Perpetual'!H4*0.8 -> 8640 | I6: =G6*0.5 -> 120000 | J6: =H6*0.5 -> 4320
A7: AEL-D1812-E-P | B7: AI-Stack Enterprise EDU | C7: AI-Stack Enterprise EDU Perpetual License, 1*NODE-Tier1, 1 year SUMS | D7: AI-Stack Enterprise SW License GPU | E7: (1) (2) (3) | F7: 1 | G7: =G6*8*0.8 -> 1536000 | H7: =H6*8*0.8 -> 55296 | I7: =G7*0.5 -> 768000 | J7: =H7*0.5 -> 27648
A8: AEL-G1124-E-P | B8: AI-Stack Enterprise EDU | C8: AI-Stack Enterprise EDU Perpetual License, 1*GPU-Tier1, 2 years SUMS | D8: AI-Stack Enterprise SW License GPU | E8: (1) (2) (3) | F8: 1 | G8: =G6*1.2 -> 288000 | H8: =H6*1.2 -> 10368 | I8: =G8*0.5 -> 144000 | J8: =H8*0.5 -> 5184
A9: AEL-D1824-E-P | B9: AI-Stack Enterprise EDU | C9: AI-Stack Enterprise EDU Perpetual License, 1*NODE-Tier1, 2 years SUMS | D9: AI-Stack Enterprise SW License GPU | E9: (1) (2) (3) | F9: 1 | G9: =G8*8*0.8 -> 1843200 | H9: =H8*8*0.8 -> 66355.2 | I9: =G9*0.5 -> 921600 | J9: =H9*0.5 -> 33177.6
A10: AEL-G1136-E-P | B10: AI-Stack Enterprise EDU | C10: AI-Stack Enterprise EDU Perpetual License, 1*GPU-Tier1, 3 years SUMS | D10: AI-Stack Enterprise SW License GPU | E10: (1) (2) (3) | F10: 1 | G10: =G6*1.4 -> 336000 | H10: =H6*1.4 -> 12096 | I10: =G10*0.5 -> 168000 | J10: =H10*0.5 -> 6048
A11: AEL-D1836-E-P | B11: AI-Stack Enterprise EDU | C11: AI-Stack Enterprise EDU Perpetual License, 1*NODE-Tier1, 3 years SUMS | D11: AI-Stack Enterprise SW License GPU | E11: (1) (2) (3) | F11: 1 | G11: =G10*8*0.8 -> 2150400 | H11: =H10*8*0.8 -> 77414.4 | I11: =G11*0.5 -> 1075200 | J11: =H11*0.5 -> 38707.2
A12: AER-G1112-E-P | B12: AI-Stack Enterprise EDU | C12: AI-Stack Enterprise EDU SUMS Renewal, 1*GPU-Tier1, 1 year | D12: AI-Stack Enterprise SUMS GPU | E12: (2) (3) | F12: 1 | G12: =G6*0.2 -> 48000 | H12: =H6*0.2 -> 1728 | I12: =G12*0.5 -> 24000 | J12: =H12*0.5 -> 864
A13: AER-D1812-E-P | B13: AI-Stack Enterprise EDU | C13: AI-Stack Enterprise EDU SUMS Renewal, 1*NODE-Tier1, 1 year | D13: AI-Stack Enterprise SUMS GPU | E13: (2) (3) | F13: 1 | G13: =G12*8*0.8 -> 307200 | H13: =H12*8*0.8 -> 11059.2 | I13: =G13*0.5 -> 153600 | J13: =H13*0.5 -> 5529.6
A14: AEU-G1100-E-P | B14: AI-Stack Enterprise EDU | C14: AI-Stack Express EDU to Enterprise EDU Perpetual License Upgrade for 1*GPU-Tier1 | D14: Express-to-Enterprise Upgrade GPU | E14: (3) (4) | F14: 1 | G14: =(G6-G41)*1.3 -> 104000 | H14: =(H6-H41)*1.3 -> 3744 | I14: =G14*0.5 -> 52000 | J14: =H14*0.5 -> 1872
A15: AEU-D1800-E-P | B15: AI-Stack Enterprise EDU | C15: AI-Stack Express EDU to Enterprise EDU Perpetual License Upgrade for 1*NODE-Tier1 | D15: Express-to-Enterprise Upgrade GPU | E15: (3) (4) | F15: 1 | G15: =G14*8*0.8 -> 665600 | H15: =H14*8*0.8 -> 23961.6 | I15: =G15*0.5 -> 332800 | J15: =H15*0.5 -> 11980.8
A17: AEL-G2112-E-P | B17: AI-Stack Enterprise EDU | C17: AI-Stack Enterprise EDU Perpetual License, 1*GPU-Tier2, 1 year SUMS | D17: AI-Stack Enterprise SW License GPU | E17: (1) (2) (3) | F17: 1 | G17: =G6/2 -> 120000 | H17: =H6/2 -> 4320 | I17: =G17*0.5 -> 60000 | J17: =H17*0.5 -> 2160
A18: AEL-D2812-E-P | B18: AI-Stack Enterprise EDU | C18: AI-Stack Enterprise EDU Perpetual License, 1*NODE-Tier2, 1 year SUMS | D18: AI-Stack Enterprise SW License GPU | E18: (1) (2) (3) | F18: 1 | G18: =G17*8*0.8 -> 768000 | H18: =H17*8*0.8 -> 27648 | I18: =G18*0.5 -> 384000 | J18: =H18*0.5 -> 13824
A19: AEL-G2124-E-P | B19: AI-Stack Enterprise EDU | C19: AI-Stack Enterprise EDU Perpetual License, 1*GPU-Tier2, 2 years SUMS | D19: AI-Stack Enterprise SW License GPU | E19: (1) (2) (3) | F19: 1 | G19: =G17*1.2 -> 144000 | H19: =H17*1.2 -> 5184 | I19: =G19*0.5 -> 72000 | J19: =H19*0.5 -> 2592
A20: AEL-D2824-E-P | B20: AI-Stack Enterprise EDU | C20: AI-Stack Enterprise EDU Perpetual License, 1*NODE-Tier2, 2 years SUMS | D20: AI-Stack Enterprise SW License GPU | E20: (1) (2) (3) | F20: 1 | G20: =G19*8*0.8 -> 921600 | H20: =H19*8*0.8 -> 33177.6 | I20: =G20*0.5 -> 460800 | J20: =H20*0.5 -> 16588.8
A21: AEL-G2136-E-P | B21: AI-Stack Enterprise EDU | C21: AI-Stack Enterprise EDU Perpetual License, 1*GPU-Tier2, 3 years SUMS | D21: AI-Stack Enterprise SW License GPU | E21: (1) (2) (3) | F21: 1 | G21: =G17*1.4 -> 168000 | H21: =H17*1.4 -> 6048 | I21: =G21*0.5 -> 84000 | J21: =H21*0.5 -> 3024
A22: AEL-D2836-E-P | B22: AI-Stack Enterprise EDU | C22: AI-Stack Enterprise EDU Perpetual License, 1*NODE-Tier2, 3 years SUMS | D22: AI-Stack Enterprise SW License GPU | E22: (1) (2) (3) | F22: 1 | G22: =G21*8*0.8 -> 1075200 | H22: =H21*8*0.8 -> 38707.2 | I22: =G22*0.5 -> 537600 | J22: =H22*0.5 -> 19353.6
A23: AER-G2112-E-P | B23: AI-Stack Enterprise EDU | C23: AI-Stack Enterprise EDU SUMS Renewal, 1*GPU-Tier2, 1 year | D23: AI-Stack Enterprise SUMS GPU | E23: (2) (3) | F23: 1 | G23: =G17*0.2 -> 24000 | H23: =H17*0.2 -> 864 | I23: =G23*0.5 -> 12000 | J23: =H23*0.5 -> 432
A24: AER-D2812-E-P | B24: AI-Stack Enterprise EDU | C24: AI-Stack Enterprise EDU SUMS Renewal, 1*NODE-Tier2, 1 year | D24: AI-Stack Enterprise SUMS GPU | E24: (2) (3) | F24: 1 | G24: =G23*8*0.8 -> 153600 | H24: =H23*8*0.8 -> 5529.6 | I24: =G24*0.5 -> 76800 | J24: =H24*0.5 -> 2764.8
A25: AEU-G2100-E-P | B25: AI-Stack Enterprise EDU | C25: AI-Stack Express EDU to Enterprise EDU Perpetual License Upgrade for 1*GPU-Tier2 | D25: Express-to-Enterprise Upgrade GPU | E25: (3) (4) | F25: 1 | G25: =G14/2 -> 52000 | H25: =H14/2 -> 1872 | I25: =G25*0.5 -> 26000 | J25: =H25*0.5 -> 936
A26: AEU-D2800-E-P | B26: AI-Stack Enterprise EDU | C26: AI-Stack Express EDU to Enterprise EDU Perpetual License Upgrade for 1*NODE-Tier2 | D26: Express-to-Enterprise Upgrade GPU | E26: (3) (4) | F26: 1 | G26: =G25*8*0.8 -> 332800 | H26: =H25*8*0.8 -> 11980.8 | I26: =G26*0.5 -> 166400 | J26: =H26*0.5 -> 5990.4
A28: AEL-G3112-E-P | B28: AI-Stack Enterprise EDU | C28: AI-Stack Enterprise EDU Perpetual License, 1*GPU-Tier3, 1 year SUMS | D28: AI-Stack Enterprise SW License GPU | E28: (1) (2) (3) | F28: 1 | G28: =G6/4 -> 60000 | H28: =H6/4 -> 2160 | I28: =G28*0.5 -> 30000 | J28: =H28*0.5 -> 1080
A29: AEL-D3812-E-P | B29: AI-Stack Enterprise EDU | C29: AI-Stack Enterprise EDU Perpetual License, 1*NODE-Tier3, 1 year SUMS | D29: AI-Stack Enterprise SW License GPU | E29: (1) (2) (3) | F29: 1 | G29: =G28*8*0.8 -> 384000 | H29: =H28*8*0.8 -> 13824 | I29: =G29*0.5 -> 192000 | J29: =H29*0.5 -> 6912
A30: AEL-G3124-E-P | B30: AI-Stack Enterprise EDU | C30: AI-Stack Enterprise EDU Perpetual License, 1*GPU-Tier3, 2 years SUMS | D30: AI-Stack Enterprise SW License GPU | E30: (1) (2) (3) | F30: 1 | G30: =G28*1.2 -> 72000 | H30: =H28*1.2 -> 2592 | I30: =G30*0.5 -> 36000 | J30: =H30*0.5 -> 1296
A31: AEL-D3824-E-P | B31: AI-Stack Enterprise EDU | C31: AI-Stack Enterprise EDU Perpetual License, 1*NODE-Tier3, 2 years SUMS | D31: AI-Stack Enterprise SW License GPU | E31: (1) (2) (3) | F31: 1 | G31: =G30*8*0.8 -> 460800 | H31: =H30*8*0.8 -> 16588.8 | I31: =G31*0.5 -> 230400 | J31: =H31*0.5 -> 8294.4
A32: AEL-G3136-E-P | B32: AI-Stack Enterprise EDU | C32: AI-Stack Enterprise EDU Perpetual License, 1*GPU-Tier3, 3 years SUMS | D32: AI-Stack Enterprise SW License GPU | E32: (1) (2) (3) | F32: 1 | G32: =G28*1.4 -> 84000 | H32: =H28*1.4 -> 3024 | I32: =G32*0.5 -> 42000 | J32: =H32*0.5 -> 1512
A33: AEL-D3836-E-P | B33: AI-Stack Enterprise EDU | C33: AI-Stack Enterprise EDU Perpetual License, 1*NODE-Tier3, 3 years SUMS | D33: AI-Stack Enterprise SW License GPU | E33: (1) (2) (3) | F33: 1 | G33: =G32*8*0.8 -> 537600 | H33: =H32*8*0.8 -> 19353.6 | I33: =G33*0.5 -> 268800 | J33: =H33*0.5 -> 9676.8
A34: AER-G3112-E-P | B34: AI-Stack Enterprise EDU | C34: AI-Stack Enterprise EDU SUMS Renewal, 1*GPU-Tier3, 1 year | D34: AI-Stack Enterprise SUMS GPU | E34: (2) (3) | F34: 1 | G34: =G28*0.2 -> 12000 | H34: =H28*0.2 -> 432 | I34: =G34*0.5 -> 6000 | J34: =H34*0.5 -> 216
A35: AER-D3812-E-P | B35: AI-Stack Enterprise EDU | C35: AI-Stack Enterprise EDU SUMS Renewal, 1*NODE-Tier3, 1 year | D35: AI-Stack Enterprise SUMS GPU | E35: (2) (3) | F35: 1 | G35: =G34*8*0.8 -> 76800 | H35: =H34*8*0.8 -> 2764.8 | I35: =G35*0.5 -> 38400 | J35: =H35*0.5 -> 1382.4
A36: AEU-G3100-E-P | B36: AI-Stack Enterprise EDU | C36: AI-Stack Express EDU to Enterprise EDU Perpetual License Upgrade for 1*GPU-Tier3 | D36: Express-to-Enterprise Upgrade GPU | E36: (3) (4) | F36: 1 | G36: =G25/2 -> 26000 | H36: =H25/2 -> 936 | I36: =G36*0.5 -> 13000 | J36: =H36*0.5 -> 468
A37: AEU-D3800-E-P | B37: AI-Stack Enterprise EDU | C37: AI-Stack Express EDU to Enterprise EDU Perpetual License Upgrade for 1*NODE-Tier3 | D37: Express-to-Enterprise Upgrade GPU | E37: (3) (4) | F37: 1 | G37: =G36*8*0.8 -> 166400 | H37: =H36*8*0.8 -> 5990.4 | I37: =G37*0.5 -> 83200 | J37: =H37*0.5 -> 2995.2
A39: AI-Stack Express Perpetual License for Education
A40: Part Number | B40: Product | C40: Description | D40: Type | E40: Terms & Conditions | F40: MOQ | G40: List Price (TWD) | H40: List Price (USD) | I40: Price for Distributor (TWD) | J40: Price for Distributor (USD)
A41: AXL-G1112-E-P | B41: AI-Stack Express EDU | C41: AI-Stack Express EDU Perpetual License, 1*GPU-Tier1, 1 year SUMS | D41: AI-Stack Express SW License GPU | E41: (1) (2) (3) | F41: 1 | G41: ='AI-Stack Commercial Perpetual'!G39*0.8 -> 160000 | H41: ='AI-Stack Commercial Perpetual'!H39*0.8 -> 5760 | I41: =G41/2 -> 80000 | J41: =H41/2 -> 2880
A42: AXL-D1812-E-P | B42: AI-Stack Express EDU | C42: AI-Stack Express EDU Perpetual License, 1*NODE-Tier1, 1 year SUMS | D42: AI-Stack Express SW License GPU | E42: (1) (2) (3) | F42: 1 | G42: =G41*8*0.8 -> 1024000 | H42: =H41*8*0.8 -> 36864 | I42: =G42/2 -> 512000 | J42: =H42/2 -> 18432
A43: AXL-G1124-E-P | B43: AI-Stack Express EDU | C43: AI-Stack Express EDU Perpetual License, 1*GPU-Tier1, 2 years SUMS | D43: AI-Stack Express SW License GPU | E43: (1) (2) (3) | F43: 1 | G43: =G41*1.2 -> 192000 | H43: =H41*1.2 -> 6912 | I43: =G43/2 -> 96000 | J43: =H43/2 -> 3456
A44: AXL-D1824-E-P | B44: AI-Stack Express EDU | C44: AI-Stack Express EDU Perpetual License, 1*NODE-Tier1, 2 years SUMS | D44: AI-Stack Express SW License GPU | E44: (1) (2) (3) | F44: 1 | G44: =G43*8*0.8 -> 1228800 | H44: =H43*8*0.8 -> 44236.8 | I44: =G44/2 -> 614400 | J44: =H44/2 -> 22118.4
A45: AXL-G1136-E-P | B45: AI-Stack Express EDU | C45: AI-Stack Express EDU Perpetual License, 1*GPU-Tier1, 3 years SUMS | D45: AI-Stack Express SW License GPU | E45: (1) (2) (3) | F45: 1 | G45: =G41*1.4 -> 224000 | H45: =H41*1.4 -> 8064 | I45: =G45/2 -> 112000 | J45: =H45/2 -> 4032
A46: AXL-D1836-E-P | B46: AI-Stack Express EDU | C46: AI-Stack Express EDU Perpetual License, 1*NODE-Tier1, 3 years SUMS | D46: AI-Stack Express SW License GPU | E46: (1) (2) (3) | F46: 1 | G46: =G45*8*0.8 -> 1433600 | H46: =H45*8*0.8 -> 51609.6 | I46: =G46/2 -> 716800 | J46: =H46/2 -> 25804.8
A47: AXR-G1112-E-P | B47: AI-Stack Express EDU | C47: AI-Stack Express EDU SUMS Renewal, 1*GPU-Tier1, 1 year | D47: AI-Stack Express SUMS GPU | E47: (2) (3) | F47: 1 | G47: =G41*0.2 -> 32000 | H47: =H41*0.2 -> 1152 | I47: =G47/2 -> 16000 | J47: =H47/2 -> 576
A48: AXR-D1812-E-P | B48: AI-Stack Express EDU | C48: AI-Stack Express EDU SUMS Renewal, 1*NODE-Tier1, 1 year | D48: AI-Stack Express SUMS GPU | E48: (2) (3) | F48: 1 | G48: =G47*8*0.8 -> 204800 | H48: =H47*8*0.8 -> 7372.8 | I48: =G48/2 -> 102400 | J48: =H48/2 -> 3686.4
A50: AXL-G2112-E-P | B50: AI-Stack Express EDU | C50: AI-Stack Express EDU Perpetual License, 1*GPU-Tier2, 1 year SUMS | D50: AI-Stack Express SW License GPU | E50: (1) (2) (3) | F50: 1 | G50: =G41/2 -> 80000 | H50: =H41/2 -> 2880 | I50: =G50/2 -> 40000 | J50: =H50/2 -> 1440
A51: AXL-D2812-E-P | B51: AI-Stack Express EDU | C51: AI-Stack Express EDU Perpetual License, 1*NODE-Tier2, 1 year SUMS | D51: AI-Stack Express SW License GPU | E51: (1) (2) (3) | F51: 1 | G51: =G50*8*0.8 -> 512000 | H51: =H50*8*0.8 -> 18432 | I51: =G51/2 -> 256000 | J51: =H51/2 -> 9216
A52: AXL-G2124-E-P | B52: AI-Stack Express EDU | C52: AI-Stack Express EDU Perpetual License, 1*GPU-Tier2, 2 years SUMS | D52: AI-Stack Express SW License GPU | E52: (1) (2) (3) | F52: 1 | G52: =G50*1.2 -> 96000 | H52: =H50*1.2 -> 3456 | I52: =G52/2 -> 48000 | J52: =H52/2 -> 1728
A53: AXL-D2824-E-P | B53: AI-Stack Express EDU | C53: AI-Stack Express EDU Perpetual License, 1*NODE-Tier2, 2 years SUMS | D53: AI-Stack Express SW License GPU | E53: (1) (2) (3) | F53: 1 | G53: =G52*8*0.8 -> 614400 | H53: =H52*8*0.8 -> 22118.4 | I53: =G53/2 -> 307200 | J53: =H53/2 -> 11059.2
A54: AXL-G2136-E-P | B54: AI-Stack Express EDU | C54: AI-Stack Express EDU Perpetual License, 1*GPU-Tier2, 3 years SUMS | D54: AI-Stack Express SW License GPU | E54: (1) (2) (3) | F54: 1 | G54: =G50*1.4 -> 112000 | H54: =H50*1.4 -> 4032 | I54: =G54/2 -> 56000 | J54: =H54/2 -> 2016
A55: AXL-D2836-E-P | B55: AI-Stack Express EDU | C55: AI-Stack Express EDU Perpetual License, 1*NODE-Tier2, 3 years SUMS | D55: AI-Stack Express SW License GPU | E55: (1) (2) (3) | F55: 1 | G55: =G54*8*0.8 -> 716800 | H55: =H54*8*0.8 -> 25804.8 | I55: =G55/2 -> 358400 | J55: =H55/2 -> 12902.4
A56: AXR-G2112-E-P | B56: AI-Stack Express EDU | C56: AI-Stack Express EDU SUMS Renewal, 1*GPU-Tier2, 1 year | D56: AI-Stack Express SUMS GPU | E56: (2) (3) | F56: 1 | G56: =G50*0.2 -> 16000 | H56: =H50*0.2 -> 576 | I56: =G56/2 -> 8000 | J56: =H56/2 -> 288
A57: AXR-D2812-E-P | B57: AI-Stack Express EDU | C57: AI-Stack Express EDU SUMS Renewal, 1*NODE-Tier2, 1 year | D57: AI-Stack Express SUMS GPU | E57: (2) (3) | F57: 1 | G57: =G56*8*0.8 -> 102400 | H57: =H56*8*0.8 -> 3686.4 | I57: =G57/2 -> 51200 | J57: =H57/2 -> 1843.2
A59: AXL-G3112-E-P | B59: AI-Stack Express EDU | C59: AI-Stack Express EDU Perpetual License, 1*GPU-Tier3, 1 year SUMS | D59: AI-Stack Express SW License GPU | E59: (1) (2) (3) | F59: 1 | G59: =G41/4 -> 40000 | H59: =H41/4 -> 1440 | I59: =G59/2 -> 20000 | J59: =H59/2 -> 720
A60: AXL-D3812-E-P | B60: AI-Stack Express EDU | C60: AI-Stack Express EDU Perpetual License, 1*NODE-Tier3, 1 year SUMS | D60: AI-Stack Express SW License GPU | E60: (1) (2) (3) | F60: 1 | G60: =G59*8*0.8 -> 256000 | H60: =H59*8*0.8 -> 9216 | I60: =G60/2 -> 128000 | J60: =H60/2 -> 4608
A61: AXL-G3124-E-P | B61: AI-Stack Express EDU | C61: AI-Stack Express EDU Perpetual License, 1*GPU-Tier3, 2 years SUMS | D61: AI-Stack Express SW License GPU | E61: (1) (2) (3) | F61: 1 | G61: =G59*1.2 -> 48000 | H61: =H59*1.2 -> 1728 | I61: =G61/2 -> 24000 | J61: =H61/2 -> 864
A62: AXL-D3824-E-P | B62: AI-Stack Express EDU | C62: AI-Stack Express EDU Perpetual License, 1*NODE-Tier3, 2 years SUMS | D62: AI-Stack Express SW License GPU | E62: (1) (2) (3) | F62: 1 | G62: =G61*8*0.8 -> 307200 | H62: =H61*8*0.8 -> 11059.2 | I62: =G62/2 -> 153600 | J62: =H62/2 -> 5529.6
A63: AXL-G3136-E-P | B63: AI-Stack Express EDU | C63: AI-Stack Express EDU Perpetual License, 1*GPU-Tier3, 3 years SUMS | D63: AI-Stack Express SW License GPU | E63: (1) (2) (3) | F63: 1 | G63: =G59*1.4 -> 56000 | H63: =H59*1.4 -> 2016 | I63: =G63/2 -> 28000 | J63: =H63/2 -> 1008
A64: AXL-D3836-E-P | B64: AI-Stack Express EDU | C64: AI-Stack Express EDU Perpetual License, 1*NODE-Tier3, 3 years SUMS | D64: AI-Stack Express SW License GPU | E64: (1) (2) (3) | F64: 1 | G64: =G63*8*0.8 -> 358400 | H64: =H63*8*0.8 -> 12902.4 | I64: =G64/2 -> 179200 | J64: =H64/2 -> 6451.2
A65: AXR-G3112-E-P | B65: AI-Stack Express EDU | C65: AI-Stack Express EDU SUMS Renewal, 1*GPU-Tier3, 1 year | D65: AI-Stack Express SUMS GPU | E65: (2) (3) | F65: 1 | G65: =G59*0.2 -> 8000 | H65: =H59*0.2 -> 288 | I65: =G65/2 -> 4000 | J65: =H65/2 -> 144
A66: AXR-D3812-E-P | B66: AI-Stack Express EDU | C66: AI-Stack Express EDU SUMS Renewal, 1*NODE-Tier3, 1 year | D66: AI-Stack Express SUMS GPU | E66: (2) (3) | F66: 1 | G66: =G65*8*0.8 -> 51200 | H66: =H65*8*0.8 -> 1843.2 | I66: =G66/2 -> 25600 | J66: =H66/2 -> 921.6
A68: *1 NODE consists of 8 GPUs

Sheet AI-Stack Education Subscription
A1: 教育版支援的單位及範圍(規則)
A2: 數位無限教育版軟體優惠授權及其相關的軟體保固(MA/SUMS) ，僅售予教育部全球資訊網所認定之各級學校及合格之非盈利教育機構 ，及中央或地方政府教育主管機關為提供各級學校使用之統籌計劃，用於非屬營利目的之教學、研究、及其他支持教育目的相關之師生與教職人員之使用，不得另行轉售。任何商業或以營利為目的之用途均不得安裝與使用。
A3: All prices without taxes
A4: AI-Stack Enterprise Subscription for Education
A5: Part Number | B5: Product | C5: Description | D5: Type | E5: Terms & Conditions | F5: MOQ | G5: List Price (TWD) | H5: List Price (USD) | I5: Price for Distributor (TWD) | J5: Price for Distributor (USD)
A6: AEL-G1112-E-S | B6: AI-Stack Enterprise EDU | C6: AI-Stack Enterprise EDU Subscription, 1*GPU-Tier1, 1 year SUMS | D6: AI-Stack Enterprise SW Subscription GPU | E6: (1) (2) (3) | F6: 1 | G6: ='AI-Stack Commercial Subscriptio'!G4*0.8 -> 120000 | H6: ='AI-Stack Commercial Subscriptio'!H4*0.8 -> 4320 | I6: =G6*0.5 -> 60000 | J6: =H6*0.5 -> 2160
A7: AEL-D1812-E-S | B7: AI-Stack Enterprise EDU | C7: AI-Stack Enterprise EDU Subscription, 1*NODE-Tier1, 1 year SUMS | D7: AI-Stack Enterprise SW Subscription GPU | E7: (1) (2) (3) | F7: 1 | G7: =G6*8*0.8 -> 768000 | H7: =H6*8*0.8 -> 27648 | I7: =G7*0.5 -> 384000 | J7: =H7*0.5 -> 13824
A8: AEL-G1124-E-S | B8: AI-Stack Enterprise EDU | C8: AI-Stack Enterprise EDU Subscription, 1*GPU-Tier1, 2 years SUMS | D8: AI-Stack Enterprise SW Subscription GPU | E8: (1) (2) (3) | F8: 1 | G8: =G6*1.2 -> 144000 | H8: =H6*1.2 -> 5184 | I8: =G8*0.5 -> 72000 | J8: =H8*0.5 -> 2592
A9: AEL-D1824-E-S | B9: AI-Stack Enterprise EDU | C9: AI-Stack Enterprise EDU Subscription, 1*NODE-Tier1, 2 years SUMS | D9: AI-Stack Enterprise SW Subscription GPU | E9: (1) (2) (3) | F9: 1 | G9: =G8*8*0.8 -> 921600 | H9: =H8*8*0.8 -> 33177.6 | I9: =G9*0.5 -> 460800 | J9: =H9*0.5 -> 16588.8
A10: AEL-G1136-E-S | B10: AI-Stack Enterprise EDU | C10: AI-Stack Enterprise EDU Subscription, 1*GPU-Tier1, 3 years SUMS | D10: AI-Stack Enterprise SW Subscription GPU | E10: (1) (2) (3) | F10: 1 | G10: =G6*1.4 -> 168000 | H10: =H6*1.4 -> 6048 | I10: =G10*0.5 -> 84000 | J10: =H10*0.5 -> 3024
A11: AEL-D1836-E-S | B11: AI-Stack Enterprise EDU | C11: AI-Stack Enterprise EDU Subscription, 1*NODE-Tier1, 3 years SUMS | D11: AI-Stack Enterprise SW Subscription GPU | E11: (1) (2) (3) | F11: 1 | G11: =G10*8*0.8 -> 1075200 | H11: =H10*8*0.8 -> 38707.2 | I11: =G11*0.5 -> 537600 | J11: =H11*0.5 -> 19353.6
A12: AEU-G1100-E-S | B12: AI-Stack Enterprise EDU | C12: AI-Stack Express EDU to Enterprise EDU Subscription Upgrade for 1*GPU-Tier1 | D12: Express-to-Enterprise Upgrade GPU | E12: (3) (4) | F12: 1 | G12: =(G6-G35)*1.3 -> 52000 | H12: =(H6-H35)*1.3 -> 1872 | I12: =G12*0.5 -> 26000 | J12: =H12*0.5 -> 936
A13: AEU-D1800-E-S | B13: AI-Stack Enterprise EDU | C13: AI-Stack Express EDU to Enterprise EDU Subscription Upgrade for 1*NODE-Tier1 | D13: Express-to-Enterprise Upgrade GPU | E13: (3) (4) | F13: 1 | G13: =G12*8*0.8 -> 332800 | H13: =H12*8*0.8 -> 11980.8 | I13: =G13*0.5 -> 166400 | J13: =H13*0.5 -> 5990.4
A15: AEL-G2112-E-S | B15: AI-Stack Enterprise EDU | C15: AI-Stack Enterprise EDU Subscription, 1*GPU-Tier2, 1 year SUMS | D15: AI-Stack Enterprise SW Subscription GPU | E15: (1) (2) (3) | F15: 1 | G15: =G6/2 -> 60000 | H15: =H6/2 -> 2160 | I15: =G15*0.5 -> 30000 | J15: =H15*0.5 -> 1080
A16: AEL-D2812-E-S | B16: AI-Stack Enterprise EDU | C16: AI-Stack Enterprise EDU Subscription, 1*NODE-Tier2, 1 year SUMS | D16: AI-Stack Enterprise SW Subscription GPU | E16: (1) (2) (3) | F16: 1 | G16: =G15*8*0.8 -> 384000 | H16: =H15*8*0.8 -> 13824 | I16: =G16*0.5 -> 192000 | J16: =H16*0.5 -> 6912
A17: AEL-G2124-E-S | B17: AI-Stack Enterprise EDU | C17: AI-Stack Enterprise EDU Subscription, 1*GPU-Tier2, 2 years SUMS | D17: AI-Stack Enterprise SW Subscription GPU | E17: (1) (2) (3) | F17: 1 | G17: =G15*1.2 -> 72000 | H17: =H15*1.2 -> 2592 | I17: =G17*0.5 -> 36000 | J17: =H17*0.5 -> 1296
A18: AEL-D2824-E-S | B18: AI-Stack Enterprise EDU | C18: AI-Stack Enterprise EDU Subscription, 1*NODE-Tier2, 2 years SUMS | D18: AI-Stack Enterprise SW Subscription GPU | E18: (1) (2) (3) | F18: 1 | G18: =G17*8*0.8 -> 460800 | H18: =H17*8*0.8 -> 16588.8 | I18: =G18*0.5 -> 230400 | J18: =H18*0.5 -> 8294.4
A19: AEL-G2136-E-S | B19: AI-Stack Enterprise EDU | C19: AI-Stack Enterprise EDU Subscription, 1*GPU-Tier2, 3 years SUMS | D19: AI-Stack Enterprise SW Subscription GPU | E19: (1) (2) (3) | F19: 1 | G19: =G15*1.4 -> 84000 | H19: =H15*1.4 -> 3024 | I19: =G19*0.5 -> 42000 | J19: =H19*0.5 -> 1512
A20: AEL-D2836-E-S | B20: AI-Stack Enterprise EDU | C20: AI-Stack Enterprise EDU Subscription, 1*NODE-Tier2, 3 years SUMS | D20: AI-Stack Enterprise SW Subscription GPU | E20: (1) (2) (3) | F20: 1 | G20: =G19*8*0.8 -> 537600 | H20: =H19*8*0.8 -> 19353.6 | I20: =G20*0.5 -> 268800 | J20: =H20*0.5 -> 9676.8
A21: AEU-G2100-E-S | B21: AI-Stack Enterprise EDU | C21: AI-Stack Express EDU to Enterprise EDU Subscription Upgrade for 1*GPU-Tier2 | D21: Express-to-Enterprise Upgrade GPU | E21: (3) (4) | F21: 1 | G21: =G12/2 -> 26000 | H21: =H12/2 -> 936 | I21: =G21*0.5 -> 13000 | J21: =H21*0.5 -> 468
A22: AEU-D2800-E-S | B22: AI-Stack Enterprise EDU | C22: AI-Stack Express EDU to Enterprise EDU Subscription Upgrade for 1*NODE-Tier2 | D22: Express-to-Enterprise Upgrade GPU | E22: (3) (4) | F22: 1 | G22: =G21*8*0.8 -> 166400 | H22: =H21*8*0.8 -> 5990.4 | I22: =G22*0.5 -> 83200 | J22: =H22*0.5 -> 2995.2
A24: AEL-G3112-E-S | B24: AI-Stack Enterprise EDU | C24: AI-Stack Enterprise EDU Subscription, 1*GPU-Tier3, 1 year SUMS | D24: AI-Stack Enterprise SW Subscription GPU | E24: (1) (2) (3) | F24: 1 | G24: =G6/4 -> 30000 | H24: =H6/4 -> 1080 | I24: =G24*0.5 -> 15000 | J24: =H24*0.5 -> 540
A25: AEL-D3812-E-S | B25: AI-Stack Enterprise EDU | C25: AI-Stack Enterprise EDU Subscription, 1*NODE-Tier3, 1 year SUMS | D25: AI-Stack Enterprise SW Subscription GPU | E25: (1) (2) (3) | F25: 1 | G25: =G24*8*0.8 -> 192000 | H25: =H24*8*0.8 -> 6912 | I25: =G25*0.5 -> 96000 | J25: =H25*0.5 -> 3456
A26: AEL-G3124-E-S | B26: AI-Stack Enterprise EDU | C26: AI-Stack Enterprise EDU Subscription, 1*GPU-Tier3, 2 years SUMS | D26: AI-Stack Enterprise SW Subscription GPU | E26: (1) (2) (3) | F26: 1 | G26: =G24*1.2 -> 36000 | H26: =H24*1.2 -> 1296 | I26: =G26*0.5 -> 18000 | J26: =H26*0.5 -> 648
A27: AEL-D3824-E-S | B27: AI-Stack Enterprise EDU | C27: AI-Stack Enterprise EDU Subscription, 1*NODE-Tier3, 2 years SUMS | D27: AI-Stack Enterprise SW Subscription GPU | E27: (1) (2) (3) | F27: 1 | G27: =G26*8*0.8 -> 230400 | H27: =H26*8*0.8 -> 8294.4 | I27: =G27*0.5 -> 115200 | J27: =H27*0.5 -> 4147.2
A28: AEL-G3136-E-S | B28: AI-Stack Enterprise EDU | C28: AI-Stack Enterprise EDU Subscription, 1*GPU-Tier3, 3 years SUMS | D28: AI-Stack Enterprise SW Subscription GPU | E28: (1) (2) (3) | F28: 1 | G28: =G24*1.4 -> 42000 | H28: =H24*1.4 -> 1512 | I28: =G28*0.5 -> 21000 | J28: =H28*0.5 -> 756
A29: AEL-D3836-E-S | B29: AI-Stack Enterprise EDU | C29: AI-Stack Enterprise EDU Subscription, 1*NODE-Tier3, 3 years SUMS | D29: AI-Stack Enterprise SW Subscription GPU | E29: (1) (2) (3) | F29: 1 | G29: =G28*8*0.8 -> 268800 | H29: =H28*8*0.8 -> 9676.8 | I29: =G29*0.5 -> 134400 | J29: =H29*0.5 -> 4838.4
A30: AEU-G3100-E-S | B30: AI-Stack Enterprise EDU | C30: AI-Stack Express EDU to Enterprise EDU Subscription Upgrade for 1*GPU-Tier3 | D30: Express-to-Enterprise Upgrade GPU | E30: (3) (4) | F30: 1 | G30: =G21/2 -> 13000 | H30: =H21/2 -> 468 | I30: =G30*0.5 -> 6500 | J30: =H30*0.5 -> 234
A31: AEU-D3800-E-S | B31: AI-Stack Enterprise EDU | C31: AI-Stack Express EDU to Enterprise EDU Subscription Upgrade for 1*NODE-Tier3 | D31: Express-to-Enterprise Upgrade GPU | E31: (3) (4) | F31: 1 | G31: =G30*8*0.8 -> 83200 | H31: =H30*8*0.8 -> 2995.2 | I31: =G31*0.5 -> 41600 | J31: =H31*0.5 -> 1497.6
A33: AI-Stack Express Subscription for Education
A34: Part Number | B34: Product | C34: Description | D34: Type | E34: Terms & Conditions | F34: MOQ | G34: List Price (TWD) | H34: List Price (USD) | I34: Price for Distributor (TWD) | J34: Price for Distributor (USD)
A35: AXL-G1112-E-S | B35: AI-Stack Express EDU | C35: AI-Stack Express EDU Subscription, 1*GPU-Tier1, 1 year SUMS | D35: AI-Stack Express SW Subscription GPU | E35: (1) (2) (3) | F35: 1 | G35: ='AI-Stack Commercial Subscriptio'!G33*0.8 -> 80000 | H35: ='AI-Stack Commercial Subscriptio'!H33*0.8 -> 2880 | I35: =G35/2 -> 40000 | J35: =H35/2 -> 1440
A36: AXL-D1812-E-S | B36: AI-Stack Express EDU | C36: AI-Stack Express EDU Subscription, 1*NODE-Tier1, 1 year SUMS | D36: AI-Stack Express SW Subscription GPU | E36: (1) (2) (3) | F36: 1 | G36: =G35*8*0.8 -> 512000 | H36: =H35*8*0.8 -> 18432 | I36: =G36/2 -> 256000 | J36: =H36/2 -> 9216
A37: AXL-G1124-E-S | B37: AI-Stack Express EDU | C37: AI-Stack Express EDU Subscription, 1*GPU-Tier1, 2 years SUMS | D37: AI-Stack Express SW Subscription GPU | E37: (1) (2) (3) | F37: 1 | G37: =G35*1.2 -> 96000 | H37: =H35*1.2 -> 3456 | I37: =G37/2 -> 48000 | J37: =H37/2 -> 1728
A38: AXL-D1824-E-S | B38: AI-Stack Express EDU | C38: AI-Stack Express EDU Subscription, 1*NODE-Tier1, 2 years SUMS | D38: AI-Stack Express SW Subscription GPU | E38: (1) (2) (3) | F38: 1 | G38: =G37*8*0.8 -> 614400 | H38: =H37*8*0.8 -> 22118.4 | I38: =G38/2 -> 307200 | J38: =H38/2 -> 11059.2
A39: AXL-G1136-E-S | B39: AI-Stack Express EDU | C39: AI-Stack Express EDU Subscription, 1*GPU-Tier1, 3 years SUMS | D39: AI-Stack Express SW Subscription GPU | E39: (1) (2) (3) | F39: 1 | G39: =G35*1.4 -> 112000 | H39: =H35*1.4 -> 4032 | I39: =G39/2 -> 56000 | J39: =H39/2 -> 2016
A40: AXL-D1836-E-S | B40: AI-Stack Express EDU | C40: AI-Stack Express EDU Subscription, 1*NODE-Tier1, 3 years SUMS | D40: AI-Stack Express SW Subscription GPU | E40: (1) (2) (3) | F40: 1 | G40: =G39*8*0.8 -> 716800 | H40: =H39*8*0.8 -> 25804.8 | I40: =G40/2 -> 358400 | J40: =H40/2 -> 12902.4
A42: AXL-G2112-E-S | B42: AI-Stack Express EDU | C42: AI-Stack Express EDU Subscription, 1*GPU-Tier2, 1 year SUMS | D42: AI-Stack Express SW Subscription GPU | E42: (1) (2) (3) | F42: 1 | G42: =G35/2 -> 40000 | H42: =H35/2 -> 1440 | I42: =G42/2 -> 20000 | J42: =H42/2 -> 720
A43: AXL-D2812-E-S | B43: AI-Stack Express EDU | C43: AI-Stack Express EDU Subscription, 1*NODE-Tier2, 1 year SUMS | D43: AI-Stack Express SW Subscription GPU | E43: (1) (2) (3) | F43: 1 | G43: =G42*8*0.8 -> 256000 | H43: =H42*8*0.8 -> 9216 | I43: =G43/2 -> 128000 | J43: =H43/2 -> 4608
A44: AXL-G2124-E-S | B44: AI-Stack Express EDU | C44: AI-Stack Express EDU Subscription, 1*GPU-Tier2, 2 years SUMS | D44: AI-Stack Express SW Subscription GPU | E44: (1) (2) (3) | F44: 1 | G44: =G42*1.2 -> 48000 | H44: =H42*1.2 -> 1728 | I44: =G44/2 -> 24000 | J44: =H44/2 -> 864
A45: AXL-D2824-E-S | B45: AI-Stack Express EDU | C45: AI-Stack Express EDU Subscription, 1*NODE-Tier2, 2 years SUMS | D45: AI-Stack Express SW Subscription GPU | E45: (1) (2) (3) | F45: 1 | G45: =G44*8*0.8 -> 307200 | H45: =H44*8*0.8 -> 11059.2 | I45: =G45/2 -> 153600 | J45: =H45/2 -> 5529.6
A46: AXL-G2136-E-S | B46: AI-Stack Express EDU | C46: AI-Stack Express EDU Subscription, 1*GPU-Tier2, 3 years SUMS | D46: AI-Stack Express SW Subscription GPU | E46: (1) (2) (3) | F46: 1 | G46: =G42*1.4 -> 56000 | H46: =H42*1.4 -> 2016 | I46: =G46/2 -> 28000 | J46: =H46/2 -> 1008
A47: AXL-D2836-E-S | B47: AI-Stack Express EDU | C47: AI-Stack Express EDU Subscription, 1*NODE-Tier2, 3 years SUMS | D47: AI-Stack Express SW Subscription GPU | E47: (1) (2) (3) | F47: 1 | G47: =G46*8*0.8 -> 358400 | H47: =H46*8*0.8 -> 12902.4 | I47: =G47/2 -> 179200 | J47: =H47/2 -> 6451.2
A49: AXL-G3112-E-S | B49: AI-Stack Express EDU | C49: AI-Stack Express EDU Subscription, 1*GPU-Tier3, 1 year SUMS | D49: AI-Stack Express SW Subscription GPU | E49: (1) (2) (3) | F49: 1 | G49: =G35/4 -> 20000 | H49: =H35/4 -> 720 | I49: =G49/2 -> 10000 | J49: =H49/2 -> 360
A50: AXL-D3812-E-S | B50: AI-Stack Express EDU | C50: AI-Stack Express EDU Subscription, 1*NODE-Tier3, 1 year SUMS | D50: AI-Stack Express SW Subscription GPU | E50: (1) (2) (3) | F50: 1 | G50: =G49*8*0.8 -> 128000 | H50: =H49*8*0.8 -> 4608 | I50: =G50/2 -> 64000 | J50: =H50/2 -> 2304
A51: AXL-G3124-E-S | B51: AI-Stack Express EDU | C51: AI-Stack Express EDU Subscription, 1*GPU-Tier3, 2 years SUMS | D51: AI-Stack Express SW Subscription GPU | E51: (1) (2) (3) | F51: 1 | G51: =G49*1.2 -> 24000 | H51: =H49*1.2 -> 864 | I51: =G51/2 -> 12000 | J51: =H51/2 -> 432
A52: AXL-D3824-E-S | B52: AI-Stack Express EDU | C52: AI-Stack Express EDU Subscription, 1*NODE-Tier3, 2 years SUMS | D52: AI-Stack Express SW Subscription GPU | E52: (1) (2) (3) | F52: 1 | G52: =G51*8*0.8 -> 153600 | H52: =H51*8*0.8 -> 5529.6 | I52: =G52/2 -> 76800 | J52: =H52/2 -> 2764.8
A53: AXL-G3136-E-S | B53: AI-Stack Express EDU | C53: AI-Stack Express EDU Subscription, 1*GPU-Tier3, 3 years SUMS | D53: AI-Stack Express SW Subscription GPU | E53: (1) (2) (3) | F53: 1 | G53: =G49*1.4 -> 28000 | H53: =H49*1.4 -> 1008 | I53: =G53/2 -> 14000 | J53: =H53/2 -> 504
A54: AXL-D3836-E-S | B54: AI-Stack Express EDU | C54: AI-Stack Express EDU Subscription, 1*NODE-Tier3, 3 years SUMS | D54: AI-Stack Express SW Subscription GPU | E54: (1) (2) (3) | F54: 1 | G54: =G53*8*0.8 -> 179200 | H54: =H53*8*0.8 -> 6451.2 | I54: =G54/2 -> 89600 | J54: =H54/2 -> 3225.6
A56: *1 NODE consists of 8 GPUs

Sheet AI-Stack Education Service
A1: 教育版支援的單位及範圍(規則)
A2: 數位無限教育版軟體優惠授權及其相關的軟體保固(MA/SUMS) ，僅售予教育部全球資訊網所認定之各級學校及合格之非盈利教育機構 ，及中央或地方政府教育主管機關為提供各級學校使用之統籌計劃，用於非屬營利目的之教學、研究、及其他支持教育目的相關之師生與教職人員之使用，不得另行轉售。任何商業或以營利為目的之用途均不得安裝與使用。
A3: All prices without taxes
A4: AI-Stack Professional Service for Education
A5: Part Number | B5: Product | C5: Description | D5: Type | E5: MOQ | F5: List Price (TWD) | G5: List Price (USD) | H5: Price for Distributor (TWD) | I5: Price for Distributor (USD)
A6: APS-C10001-E | B6: AI-Stack Professional Service | C6: AI-Stack Consultant Service, 1*Day | D6: AI-Stack Consultant Service | E6: 1 | F6: ='AI-Stack Commercial Service'!F4*0.8 -> 36000 | G6: ='AI-Stack Commercial Service'!G4*0.8 -> 1296 | H6: =F6*0.8 -> 28800 | I6: =G6*0.8 -> 1036.8
A7: APS-C05001-E | B7: AI-Stack Professional Service | C7: AI-Stack Consultant Service, 0.5*Day | D7: AI-Stack Consultant Service | E7: 1 | F7: ='AI-Stack Commercial Service'!F5*0.8 -> 20000 | G7: ='AI-Stack Commercial Service'!G5*0.8 -> 720 | H7: =F7*0.8 -> 16000 | I7: =G7*0.8 -> 576
A8: APS-T10001-E | B8: AI-Stack Professional Service | C8: AI-Stack Training Service, 1*Day | D8: AI-Stack Training Service | E8: 1 | F8: ='AI-Stack Commercial Service'!F6*0.8 -> 24000 | G8: ='AI-Stack Commercial Service'!G6*0.8 -> 864 | H8: =F8*0.8 -> 19200 | I8: =G8*0.8 -> 691.2
A9: APS-T10001-E | B9: AI-Stack Professional Service | C9: AI-Stack Training Service, 0.5*Day | D9: AI-Stack Training Service | E9: 1 | F9: ='AI-Stack Commercial Service'!F7*0.8 -> 14000 | G9: ='AI-Stack Commercial Service'!G7*0.8 -> 504 | H9: =F9*0.8 -> 11200 | I9: =G9*0.8 -> 403.2

Sheet CloudFusion Commercial
A1: All prices without taxes
A2: CloudFusion Enterprise Perpetual License for Commercial
A3: Part Number | B3: Product | C3: Description | D3: Type | E3: Terms & Conditions | F3: MOQ | G3: List Price (TWD) | H3: Price for Distributor (TWD)
A4: CEL-C0112-N | B4: CloudFusion Enterprise | C4: CloudFusion Enterprise Perpetual License, 1 CPU, 1 year SUMS | D4: CloudFusion Enterprise License 1 CPU | E4: (1) (2) | F4: 1 | G4: 83000 | H4: =G4*0.5 -> 41500
A5: CEL-C0124-N | B5: CloudFusion Enterprise | C5: CloudFusion Enterprise Perpetual License, 1 CPU, 2 years SUMS | D5: CloudFusion Enterprise License 1 CPU | E5: (1) (2) | F5: 1 | G5: =G4*1.2 -> 99600 | H5: =G5*0.5 -> 49800
A6: CEL-C0136-N | B6: CloudFusion Enterprise | C6: CloudFusion Enterprise Perpetual License, 1 CPU, 3 years SUMS | D6: CloudFusion Enterprise License 1 CPU | E6: (1) (2) | F6: 1 | G6: =G4*1.4 -> 116200 | H6: =G6*0.5 -> 58100
A7: CER-C0112-N | B7: CloudFusion Enterprise | C7: CloudFusion Enterprise SUMS Renewal, 1 CPU, 1 year | D7: CloudFusion Enterprise SUMS 1 CPU | E7: (2) | F7: 1 | G7: =G4*0.2 -> 16600 | H7: =G7*0.5 -> 8300
H8: =G8*0.5 -> 0
A9: CEL-C0612-N | B9: CloudFusion Enterprise | C9: CloudFusion Enterprise Perpetual License, 6 CPUs, 1 year SUMS | D9: CloudFusion Enterprise License 6 CPUs | E9: (1) (2) | F9: 1 | G9: 445000 | H9: =G9*0.5 -> 222500
A10: CEL-C0624-N | B10: CloudFusion Enterprise | C10: CloudFusion Enterprise Perpetual License, 6 CPUs, 2 years SUMS | D10: CloudFusion Enterprise License 6 CPUs | E10: (1) (2) | F10: 1 | G10: =G9*1.2 -> 534000 | H10: =G10*0.5 -> 267000
A11: CEL-C0636-N | B11: CloudFusion Enterprise | C11: CloudFusion Enterprise Perpetual License, 6 CPUs, 3 years SUMS | D11: CloudFusion Enterprise License 6 CPUs | E11: (1) (2) | F11: 1 | G11: =G9*1.4 -> 623000 | H11: =G11*0.5 -> 311500
A12: CER-C0612-N | B12: CloudFusion Enterprise | C12: CloudFusion Enterprise SUMS Renewal, 6 CPUs, 1 year | D12: CloudFusion Enterprise SUMS 6 CPUs | E12: (2) | F12: 1 | G12: =G11*0.2 -> 124600 | H12: =G12*0.5 -> 62300
H13: =G13*0.5 -> 0
A14: CEL-C1212-N | B14: CloudFusion Enterprise | C14: CloudFusion Enterprise Perpetual License, 12 CPUs, 1 year SUMS | D14: CloudFusion Enterprise License 12 CPUs | E14: (1) (2) | F14: 1 | G14: 833000 | H14: =G14*0.5 -> 416500
A15: CEL-C1224-N | B15: CloudFusion Enterprise | C15: CloudFusion Enterprise Perpetual License, 12 CPUs, 2 years SUMS | D15: CloudFusion Enterprise License 12 CPUs | E15: (1) (2) | F15: 1 | G15: =G14*1.2 -> 999600 | H15: =G15*0.5 -> 499800
A16: CEL-C1236-N | B16: CloudFusion Enterprise | C16: CloudFusion Enterprise Perpetual License, 12 CPUs, 3 years SUMS | D16: CloudFusion Enterprise License 12 CPUs | E16: (1) (2) | F16: 1 | G16: =G14*1.4 -> 1166200 | H16: =G16*0.5 -> 583100
A17: CER-C1212-N | B17: CloudFusion Enterprise | C17: CloudFusion Enterprise SUMS Renewal, 12 CPUs, 1 year | D17: CloudFusion Enterprise SUMS 12 CPUs | E17: (2) | F17: 1 | G17: =G16*0.2 -> 233240 | H17: =G17*0.5 -> 116620

Sheet CloudFusion Commercial Service
A1: All prices without taxes
A2: CloudFusion Professional Service for Commercial
A3: Part Number | B3: Product | C3: Description | D3: Type | E3: MOQ | F3: List Price (TWD) | G3: List Price (USD) | H3: Price for Distributor (TWD) | I3: Price for Distributor (USD)
A4: CPS-C10001-C | B4: CloudFusion Professional Service | C4: CloudFusion Consultant Service, 1*Day | D4: CloudFusion Consultant Service | E4: 1 | F4: 45000 | G4: 1620 | H4: =F4*0.8 -> 36000 | I4: =G4*0.8 -> 1296
A5: CPS-C05001-C | B5: CloudFusion Professional Service | C5: CloudFusion Consultant Service, 0.5*Day | D5: CloudFusion Consultant Service | E5: 1 | F5: 25000 | G5: 900 | H5: =F5*0.8 -> 20000 | I5: =G5*0.8 -> 720
A6: CPS-T10001-C | B6: CloudFusion Professional Service | C6: CloudFusion Training Service, 1*Day | D6: CloudFusion Training Service | E6: 1 | F6: 30000 | G6: 1080 | H6: =F6*0.8 -> 24000 | I6: =G6*0.8 -> 864
A7: CPS-T10001-C | B7: CloudFusion Professional Service | C7: CloudFusion Training Service, 0.5*Day | D7: CloudFusion Training Service | E7: 1 | F7: 17500 | G7: 630 | H7: =F7*0.8 -> 14000 | I7: =G7*0.8 -> 504

Sheet CloudFusion Education
A1: 教育版支援的單位及範圍(規則)
A2: 數位無限教育版軟體優惠授權及其相關的軟體保固(MA/SUMS) ，僅售予教育部全球資訊網所認定之各級學校及合格之非盈利教育機構 ，及中央或地方政府教育主管機關為提供各級學校使用之統籌計劃，用於非屬營利目的之教學、研究、及其他支持教育目的相關之師生與教職人員之使用，不得另行轉售。任何商業或以營利為目的之用途均不得安裝與使用。
A3: All prices without taxes
A4: CloudFusion Enterprise Perpetual License for Education
A5: Part Number | B5: Product | C5: Description | D5: Type | E5: Terms & Conditions | F5: MOQ | G5: List Price (TWD) | H5: Price for Distributor (TWD)
A6: CEL-C0112-E | B6: CloudFusion Enterprise EDU | C6: CloudFusion Enterprise EDU Perpetual License, 1 CPU, 1 year SUMS | D6: CloudFusion Enterprise License 1 CPU | E6: (1) (2) (5) | F6: 1 | G6: 66400 | H6: =G6/2 -> 33200
A7: CEL-C0124-E | B7: CloudFusion Enterprise EDU | C7: CloudFusion Enterprise EDU Perpetual License, 1 CPU, 2 years SUMS | D7: CloudFusion Enterprise License 1 CPU | E7: (1) (2) (5) | F7: 1 | G7: =G6*1.2 -> 79680 | H7: =G7/2 -> 39840
A8: CEL-C0136-E | B8: CloudFusion Enterprise EDU | C8: CloudFusion Enterprise EDU Perpetual License, 1 CPU, 3 years SUMS | D8: CloudFusion Enterprise License 1 CPU | E8: (1) (2) (5) | F8: 1 | G8: =G6*1.4 -> 92960 | H8: =G8/2 -> 46480
A9: CER-C0112-E | B9: CloudFusion Enterprise EDU | C9: CloudFusion Enterprise EDU SUMS Renewal, 1 CPU, 1 year | D9: CloudFusion Enterprise SUMS 1 CPU | E9: (2) (5) | F9: 1 | G9: =G6*0.2 -> 13280 | H9: =H6*0.2 -> 6640
A11: CEL-C0612-E | B11: CloudFusion Enterprise EDU | C11: CloudFusion Enterprise EDU Perpetual License, 6 CPUs, 1 year SUMS | D11: CloudFusion Enterprise License 6 CPUs | E11: (1) (2) (5) | F11: 1 | G11: 356000 | H11: =G11/2 -> 178000
A12: CEL-C0624-E | B12: CloudFusion Enterprise EDU | C12: CloudFusion Enterprise EDU Perpetual License, 6 CPUs, 2 years SUMS | D12: CloudFusion Enterprise License 6 CPUs | E12: (1) (2) (5) | F12: 1 | G12: =G11*1.2 -> 427200 | H12: =G12/2 -> 213600
A13: CEL-C0636-E | B13: CloudFusion Enterprise EDU | C13: CloudFusion Enterprise EDU Perpetual License, 6 CPUs, 3 years SUMS | D13: CloudFusion Enterprise License 6 CPUs | E13: (1) (2) (5) | F13: 1 | G13: =G11*1.4 -> 498400 | H13: =G13/2 -> 249200
A14: CER-C0612-E | B14: CloudFusion Enterprise EDU | C14: CloudFusion Enterprise EDU SUMS Renewal, 6 CPUs, 1 year | D14: CloudFusion Enterprise SUMS 6 CPUs | E14: (2) (5) | F14: 1 | G14: =G11*0.2 -> 71200 | H14: =H11*0.2 -> 35600
A16: CEL-C1212-E | B16: CloudFusion Enterprise EDU | C16: CloudFusion Enterprise EDU Perpetual License, 12 CPUs, 1 year SUMS | D16: CloudFusion Enterprise License 12 CPUs | E16: (1) (2) (5) | F16: 1 | G16: 666400 | H16: =G16/2 -> 333200
A17: CEL-C1224-E | B17: CloudFusion Enterprise EDU | C17: CloudFusion Enterprise EDU Perpetual License, 12 CPUs, 2 years SUMS | D17: CloudFusion Enterprise License 12 CPUs | E17: (1) (2) (5) | F17: 1 | G17: =G16*1.2 -> 799680 | H17: =G17/2 -> 399840
A18: CEL-C1236-E | B18: CloudFusion Enterprise EDU | C18: CloudFusion Enterprise EDU Perpetual License, 12 CPUs, 3 years SUMS | D18: CloudFusion Enterprise License 12 CPUs | E18: (1) (2) (5) | F18: 1 | G18: =G16*1.4 -> 932960 | H18: =G18/2 -> 466480
A19: CER-C1212-E | B19: CloudFusion Enterprise EDU | C19: CloudFusion Enterprise EDU SUMS Renewal, 12 CPUs, 1 year | D19: CloudFusion Enterprise SUMS 12 CPUs | E19: (2) (5) | F19: 1 | G19: =G16*0.2 -> 133280 | H19: =H16*0.2 -> 66640

Sheet CloudFusion Education Service
A1: 教育版支援的單位及範圍(規則)
A2: 數位無限教育版軟體優惠授權及其相關的軟體保固(MA/SUMS) ，僅售予教育部全球資訊網所認定之各級學校及合格之非盈利教育機構 ，及中央或地方政府教育主管機關為提供各級學校使用之統籌計劃，用於非屬營利目的之教學、研究、及其他支持教育目的相關之師生與教職人員之使用，不得另行轉售。任何商業或以營利為目的之用途均不得安裝與使用。
A3: All prices without taxes
A4: CloudFusion Professional Service for Education
A5: Part Number | B5: Product | C5: Description | D5: Type | E5: MOQ | F5: List Price (TWD) | G5: List Price (USD) | H5: Price for Distributor (TWD) | I5: Price for Distributor (USD)
A6: CPS-P10001-E | B6: CloudFusion Professional Service | C6: CloudFusion Consultant Service, 1*Day | D6: CloudFusion Consultant Service | E6: 1 | F6: ='CloudFusion Commercial Service'!F4*0.8 -> 36000 | G6: ='CloudFusion Commercial Service'!G4*0.8 -> 1296 | H6: =F6*0.8 -> 28800 | I6: =G6*0.8 -> 1036.8
A7: CPS-P05001-E | B7: CloudFusion Professional Service | C7: CloudFusion Consultant Service, 0.5*Day | D7: CloudFusion Consultant Service | E7: 1 | F7: ='CloudFusion Commercial Service'!F5*0.8 -> 20000 | G7: ='CloudFusion Commercial Service'!G5*0.8 -> 720 | H7: =F7*0.8 -> 16000 | I7: =G7*0.8 -> 576
A8: CPS-T10001-E | B8: CloudFusion Professional Service | C8: CloudFusion Training Service, 1*Day | D8: CloudFusion Training Service | E8: 1 | F8: ='CloudFusion Commercial Service'!F6*0.8 -> 24000 | G8: ='CloudFusion Commercial Service'!G6*0.8 -> 864 | H8: =F8*0.8 -> 19200 | I8: =G8*0.8 -> 691.2
A9: CPS-T10001-E | B9: CloudFusion Professional Service | C9: CloudFusion Training Service, 0.5*Day | D9: CloudFusion Training Service | E9: 1 | F9: ='CloudFusion Commercial Service'!F7*0.8 -> 14000 | G9: ='CloudFusion Commercial Service'!G7*0.8 -> 504 | H9: =F9*0.8 -> 11200 | I9: =G9*0.8 -> 403.2

Sheet Terms & Conditions
A1: INFINITIX Distribution Terms and Conditions (中文版)
A2: 項次 | B2: 項目 | C2: 說明 | D2: 料號編碼
A3: (1) | B3: 軟體授權 | C3: 軟體授權：提供客戶使用INFINITIX軟體的授權為不可出售、不可轉讓的權利，依個別CPU / GPU限制僅限約定預期的目的使用之，不可進行未經授權的修改或逆向工程。 | D3: #CSL, #CEL, #ALL, #AXL
A4: (2) | B4: 維護服務 | C4: (2-1)授權內含維護服務：任何軟體授權的購買皆包含至少一年的原廠軟體更新、支援與維護訂閱服務（以下簡稱SUMS）。SUMS價值如下表： (2-2)續約維護服務：軟體授權內含維護服務過期後，可另外加購SUMS服務，以取得產品更新、支援與維護，SUMS價格另議。 | D4: #CSL, #CEL, #ALL, #AXL, #CSR, #CER, #ALR, #AXR
A5: (3) | B5: GPU授權分級 | C5: GPU授權分級：授權與GPU一起使用的軟體授權及其相關原廠更新、支援與維護服務(SUMS)可能因特定NVIDIA DGX伺服器方案或不同層級的GPU而有差異（請參閱原廠公告之AI-Stack GPU層級表）。 | D5: #ALL-D/G, #ALR-D/G, #AXL-D/G, #AXR-D/G, #AXU-D/G
A6: (4) | B6: 產品升級 | C6: 產品升級：同一產品系列（即AI-Stack，CloudFusion）軟體授權可升級到更高級別的產品，剩餘期間的原廠更新、支援與維護服務(SUMS)可平行轉移。更新後的SUMS適用於升級後的產品。 | D6: #CEU, #AXU
A7: (5) | B7: 教育折扣 | C7: 教育折扣：數位無限教育版軟體優惠授權及其相關的軟體保固(MA/SUMS) ，僅售予教育部全球資訊網所認定之各級學校及合格之非盈利教育機構 ，及中央或地方政府教育主管機關為提供各級學校使用之統籌計劃，用於非屬營利目的之教學、研究、及其他支持教育目的相關之師生與教職人員使用，不得轉售。任何商業或以營利為目的之用途均不得安裝與使用。 | D7: #CSL/R-*-E, #CEL/R/U-*-E, #ALL/R-*-E, #AXL/R/U-*-E
A8: (6) | B8: 技術服務-AI框架樣板 設定服務 | C8: 技術服務-AI框架樣板(Template, 或稱模板/樣本)設定服務：由INFINITIX認證的工程師（以下稱為“工程師”）提供的專業服務，從NVIDIA NGC中選擇4個（最常用的）AI框架進行機器學習（預設樣板包括（1）Tensor Flow、（2）PyTorch、（3）MXNet、（4）Caffe，除非客戶另有要求，並且在服務開始之前經過工程師的同意，方可提供包含在此範圍內），將Docker映像打包上傳為可從AI-Stack使用者登入系統中可供選擇的樣板，並以一次性服務方式和軟體安裝同時交付，該內容適用於培訓或其他經工程師同意的項目。服務交付後，若發生任何框架/工具更新需求，則客戶應自行維護交付的樣板。此項服務不保證可以完全支援所有非NVIDIA NGC Docker映像。 | D8: #PSS-AF4*, (#AL*, #AX*)
A9: (7) | B9: 技術服務-客戶儲存系統掛載設定服務 | C9: 技術服務-客戶儲存系統掛載設定服務：由INFINITIX認證的工程師提供專業服務，透過必要的配置，以NSF和/或S3連接CloudFusion或AI-Stack與客戶現有的儲存解決方案。S3的支援程度取決於儲存方案供應商的規格與限制。INFINITIX不保證支援所有S3儲存解決方案。 | D9: #PSS-STR*
A10: (8) | B10: 技術服務-帳號權控系統串接設定服務 | C10: 技術服務-帳號權控系統串接設定服務：因應客戶現有PAM / IdM / IdAM解決方案（支援AD / LDAP或OpenID），由INFINITIX認證的工程師提供專業服務，協助調整CloudFusion或AI-Stack配置。服務完成後，客戶現有的PAM / IdM / IdAM將成為CloudFusion / AI-Stack用戶身份和登入管理的資料來源。 | D10: #PSS-PAM*
A11: (9) | B11: 技術服務-遠程培訓服務 | C11: 技術服務-遠程培訓服務是以場次為單位計算的一次性專業服務，由INFINITIX認證的產品專家或維護工程師作為講師提供之（每節講師人數為2位），透過網路以電話會議軟體為媒介，提供客戶端軟體使用者和管理人員產品培訓。培訓內容將依據標準版用戶培訓手冊的標準指南，協助學生使用和操作INFINITIX授權軟體。每節課程的學生人數以12人為上限。每次培訓服務時間應為4小時。講師（培訓服務的提供者）應提供一次Zoom或等效的視頻錄製會議，讓學生有適當的登入權限，除非客戶/學生另行提供其他方式並經講師同意，得以其他軟體或媒介進行培訓。客戶/學生應負責提供可順暢進行培訓的網路頻寬與登入權限，並提供可供參與者使用並可連網的個人電腦/筆記型電腦。 | D11: #PST-CAL*
A12: (10) | B12: 技術服務-現場培訓服務 | C12: 技術服務-現場培訓服務是以場次為單位計算的一次性專業服務，由INFINITIX認證的產品專家或維護工程師作為講師提供之（每節講師人數為2位），在客戶端或客戶指定的場所提供產品培訓。客戶的軟體使用者和管理者即學生（每節的學生人數以12人為上限）將根據《用戶培訓手冊》（標準版）的標準指南來使用和操作INFINITIX授權軟體。每次培訓服務時間應為4小時。客戶/學生應負責提供適當的培訓設施（除非講師/供應商在會前另有協議），客戶/學生應負責提供可順暢進行培訓的網路頻寬與登入權限，並提供可供參與者使用並可連網的個人電腦/筆記型電腦。 *指導員提供現場會議的差旅費用不包括在標價中，並且費用範圍應由指導員/供應商和客戶/學生在下訂單之前共同商定。 | D12: #PST-OST*
A13: (11) | B13: 技術服務-軟體安裝服務 | C13: 技術服務-軟體安裝服務是由INFINITIX認證的工程師提供的專業服務，以現場（客戶所在地）或透過網路連接遠程方式安裝INFINITIX產品。費用按工作日計算。 *不包括工程師提供現場服務的差旅費，費用範圍應由供應商/工程師和客戶在下訂單前共同商定，且不得遲於服務起始日。 | D13: #PSO-IST*
... A15: (13) | B15: 技術服務-人員到場服務 | C15: 技術服務-人員到場服務是指：購買合法授權且在保固期間之客戶，因其自身技術環境限制、人員或其他管理原因，且不可歸責於原廠或經銷商之產品瑕疵或過失遺漏等情況下，須由INFINITIX原廠、或經其認證的工程師，赴客戶指定之台灣本島內的客戶現場 (包含但不限於客戶承載授權軟體之數據中心，或客戶軟體管理人員之內部網絡接取點等所在，非原廠或其代理商工程師常規實施遠程服務之原廠或代理商工程師之日常工作地點者) 提供軟體保固、升級與排除異常等軟體維護服務。赴現客戶場現場提供服務之人員差旅費用不包括在本標價中。 | D15: #PSO-OST*
A17: INFINITIX Distribution Terms and Conditions (English Version)
A18: No | B18: Item | C18: Descriptions | D18: Applicability
A19: (1) | B19: Perpetual licenses | C19: Perpetual licenses grant customers non-sellable, non-transferrable rights to use INFINITIX software, as is and for the intended purposes only, without unauthorized modifications or re-engineering, according to the respective CPU/GPU limits. | D19: #CSL, #CEL, #ALL, #AXL
A20: (2) | B20: Maintenance Service | C20: (2-1)Maintenance Services Included in the licenses: The first year of Support, Updates and Maintenance Subscription (SUMS) is required as part of any purchase of licenses. (2-2) Renewal of Maintenance Services: After the maintenance services included in the software license expire, additional SUMS services can be purchased to obtain product updates, support, and maintenance. The pricing for SUMS is subject to further negotiation. | D20: #CSL, #CEL, #ALL, #AXL, #CSR, #CER, #ALR, #AXR
A21: (3) | B21: GPU Tier Perpetual licenses | C21: Perpetual licenses, and the associated SUMS, authorized for use with GPUs may vary by specific NVIDIA DGX server packages and/or by different GPU performance tiers (for tier classification, please refer to AI-Stack GPU Tier Table). | D21: #ALL-D/G, #ALR-D/G, #AXL-D/G, #AXR-D/G, #AXU-D/G
A22: (4) | B22: Product upgrade | C22: Perpetual licenses may be upgradeable to the higher-level products in the same product series (i.e., AI-Stack, CloudFusion), with the remaining SUMS carried over. The renewal of SUMS after upgrades shall apply to the upgraded products. | D22: #CEU, #AXU
A23: (5) | B23: Education (EDU) licenses | C23: Education (EDU) licenses (and the associated SUMS) are the licenses (and services) attached to software that are sold at a discount to the faculty affiliated with an eligible educational institution and can not be resold at any point. | D23: #CSL/R-*-E, #CEL/R/U-*-E, #ALL/R-*-E, #AXL/R/U-*-E
A24: (6) | B24: Technical Services-AI Frameworks Template Professional service | C24: Professional service by INFINITIX certified engineers (hereafter as "the Engineers") to select 4 (most frequently used) AI Frameworks for machine learning from the NVIDIA NGC (with the default templates including (1) Tensor Flow, (2) PyTorch, (3) MXNet, (4) Caffe, unless otherwise requested by the customers and agreed by the Engineers prior to the commencement of service) to package as Docker images uploaded as selectable templates accessible from the User Portal of AI-Stack, deliverable as a one-time service alongside software installation, training, or otherwise agreed by the Engineers as applicable. The customers should self-maintain the delivered templates when any framework/tool updates occurred and needed after the service. It is NOT guaranteed that all non-NVIDIA NGC Docker images can be fully supported. | D24: #PSS-AF4*, (#AL*, #AX*)
A25: (7) | B25: Technical Services-Mount Storage Configuration Professional service | C25: Professional service by INFINITIX certified engineers to hook up customers' existing storage solution(s) via NSF and/or S3 with CloudFusion or AI-Stack through necessary configurations. Support level via S3 depends upon the storage suppliers' specifications and limitations. INFINITIX does NOT guarantee full supportability for all S3-supported storage solutions. | D25: #PSS-STR*
A26: (8) | B26: Technical Services-PAM/IdM/IdAM Configuration Professional service | C26: Professional service by INFINITIX certified engineers to configure and adapt the customers' existing PAM/IdM/IdAM solutions (AD/LDAP or OpenID supported) with CloudFusion or AI-Stack. Once the service is completed, the customers' existing PAM/IdM/IdAM becomes the data source for the user identity and access management of CloudFusion/AI-Stack. | D26: #PSS-PAM*
A27: (9) | B27: Technical Services-REMOTE Training Service | C27: REMOTE Training Service is a session-based one-time professional service provided by INFINITIX certified product experts or support engineers as Instructors (instructor number per session = 2) to provide product training VIA TELECONFERENCING SOFTWARE THROUGH IP NETWORK to the customers' software users and managers as Students (student number per session <= 12) for the use and operation of the licensed INFINITIX products according to the standard guidelines of the User Training Manual (標準版用戶培訓手冊). The duration for each training service session should be 4 hours. The Instructors (suppliers of the training service) should provide a Zoom, or equivalent, video-recording meeting session with sufficient access for Students, unless otherwise provided by the customers/Students and agreed by the Instructors. The customers/Students should be responsible for the adequate Internet access and networked PCs/ Laptops suitable for attending and participating in the training sessions. | D27: #PST-CAL*
A28: (10) | B28: Technical Services-ON-SITE Training Service | C28: ON-SITE Training Service is a session-based one-time professional service provided by INFINITIX certified product experts or support engineers as Instructors (instructor number per session = 2) to provide product training ON ONE OF THE CUSTOMER'S OR CUSTOMER-DESIGNATED PREMISES to the customers' software users and managers as Students (student number per session <= 12) for the use and operation of the licensed INFINITIX products according to the standard guidelines of the User Training Manual (標準版用戶培訓手冊). The duration for each training service session should be 4 hours. The customers/Students should be responsible for the adequate training facility (unless otherwise agreed by the Instructors/supplier before the session), and the adequate Internet access and networked PCs/ Laptops suitable for participating in the training sessions. *Travel Expenses for the Instructors to provide on-site sessions are NOT included in List Price, and the coverage of expenses should be mutually agreed by the Instructors/supplier and the customers/Students before placing orders. | D28: #PST-OST*
A29: (11) | B29: Technical Services-Software Installation Service | C29: Software Installation Service is a professional service by INFINITIX certified engineers to install INFINITIX products on-site (the customers' premises) or remotely through Internet connection. Fees are calculated by man days. *Travel Expenses for the Engineers to provide on-site service are NOT included, and the coverage of expenses should be mutually agreed by the suppler/Engineers and the customers before placing orders, and no later than the commencement of service. | D29: #PSO-IST*
... A31: (13) | B31: Technical Services-Troubleshooting On-Site Service | C31: Troubleshooting On-Site Service is a billable professional service done by INFINITIX or certified Support Engineers to provide on-site trouble-shooting, upgrade, and/or maintenance services for INFINITIX software on the Customer-designated premises in the main island of Taiwan (including but not limited to the Customer's datacenters hosting the licensed INFINITIX software, or the administrators' access endpoints connected to the Customers' Intranet, whichever situated outsides INFINITIX's or the certified Support Engineers' regular working locations), in response to requests by the Customers with legitimate proofs of purchase of INFINITIX software licenses, and under a valid coverage of effective software warranty (a.k.a. MA/SUMS) periods, due to the Customers' own technical, personnel, and/or managerial restrictions, while NOT liable to INFINITIX or her resellers, with any major product defects or service negligence. *Travel Expenses for INFINITIX or the certified Support Engineers to provide Troubleshooting On-Site service are NOT included in this List Price. | D31: #PSO-OST*

Sheet AI-Stack版本功能表
A2: AI-Stack版本功能表(Express與Lite版本功能差異)

Sheet CloudFusion版本功能表
B3: 功能 | C3: 支援清單 | D3: CloudFusion Enterprise
B4: 私有雲 基礎資源串接、協同與調度 | C4: VMware與OpenStack | D4: 支援多款私有雲(不限)
B5: 公有雲 基礎資源串接、協同與調度 | C5: AWS、Microsoft Azure、 阿里雲、Google Cloud Platform | D5: 支援多款公有雲(不限)
D6: 支援客製化開發需求

Sheet AI-Stack GPU Tier對應表
A1: AI-Stack GPU Tier Support List
A2: Tier | B2: Product
A3: 1 | B3: NVIDIA: Telsa: B200, B100, H200, H100 AMD: Instinct: MI325X, MI300X, MI300A
A4: 2 | B4: NVIDIA: Tesla: A100, V100 Quodra: 6000 Ada, 5880 Ada, 5000 Ada, L40S, L40 AMD: Instinct: MI250X, MI250, MI210
A5: 3 | B5: NVIDIA: Tesla: L4, A2, A10, A16, A30, A40, A400 Quadro: 2000 Ada, 4000 Ada, 4500 Ada, A1000, A2000, A4000, A4500, A5000, A5500, A6000, RTX 4000, RTX 5000, RTX 6000, RTX 8000, T4, T400, T600, T1000, P100, P400, P600, P620, P1000, P2000, P2200, P4000, P5000, P6000, GP100, GV100 GeForce: RTX 5090, RTX 5090 D, RTX 5080, RTX 5070, RTX 5070 Ti, RTX 4090, RTX 4090 D, RTX 4080, RTX 4080 Super, RTX 4070, RTX 4070 Super, RTX 4070 Ti, RTX 4070 Ti Super, RTX 4060, RTX 4060 Ti, RTX 3090, RTX 3090 Ti, RTX 3080, RTX 3080 Ti, RTX 3070, RTX 3070 Ti, RTX 3060, RTX 3060 TI, RTX 3050, RTX 2080, RTX 2080 Super, RTX 2080 TI, RTX 2070, RTX 2070 Super, RTX 2060, RTX 2060 Super, TITAN RTX AMD: Instinct: MI100, MI60 Radeon: RX 7900 XTX, RX 7900 XT, RX 7900 GRE, RX 7800 XT, RX 7700 XT, RX 7600 XT, RX 7600, RX 6950 XT, RX 6900 XT, RX 6800 XT, RX 6800, RX 6750 XT, RX 6750 GRE, RX 6700 XT, RX 6700, RX 6650 XT, RX 6600 XT, RX 6600, RX 6500 XT, RX 6400, RX 6300, RX 5700 XT, RX 5700, RX 5600 TX, RX 5600, RX 5500 XT, RX 5500, RX 5300 XT, RX 5300
A6: 1.All GPUs in the list are CUDA/ROCm-supported. 2.GPUs in the list are supported by Infinitix AI-Stack. 3.AI-Stack may work with GPUs not listed herein, but at users' oen risks. 4.Infinitix reserves the rights to modify this Tier Table with a 30-day notice. All changes will not be retrospectively applied.

Sheet 產品保固及過保說明
A2: 數位無限產品保固及過保說明
A3: 資料來源連結如下，若說明有差異，以以下連結內容為主
A4: 數位無限產品保固及過保說明連結(點我)
A6: #原廠保固內容？
A7: 保固標的物為數位無限所提供之軟體服務系統並具備合法軟體授權。除此之外之硬體、作業系統、網路系統或其他非保固標的物之外的軟硬體系統均不在保固範圍。
A9: #保固方式？
A10: 具合法授權並於軟體保固期間內之用戶，數位無限將承諾針對軟體之程式碼瑕疵進行維護與修正，並享有技術支援服務。
A12: #保修時間?
A13: 工作日每周一至周五，上午10時至下午18時(依台灣行政院人事行政局公佈之國定假日以外視同工作日)。
A15: #如何報修?
A16: 數位無限提供電子信箱與電話聯絡方式
A17: Email： support＠INFINITIX.com
... A28: 軟體因程式碼上的瑕疵、系統服務發生異常，或必要性的功能調整、新增，例如資安漏洞修補，將由數位無限提供技術支援服務，若經檢測後需進行軟體更新或修復作業，也將由數位無限提供原廠服務。

Sheet 報價範例說明
A2: 範例一、AI-Stack報價說明
A4: 客戶有AI-Stack需求，硬體規格如下，請協助報價:
A5: 一台DELL Server(規格為:CPU*2 / 512GB RAM / 600G 15K*2 HDD/ V100 GPU卡*2片/ POWER*2)。
A8: 報價步驟:
A9: 1 | B9: 客戶是否是教育單位?
B10: 客戶回答:No
A11: 2 | B11: 請客戶提供實際的硬體規格，內建的GPU卡片為何?
B12: 依照上面的規格可以得知 GPU卡片為:"V100 GPU卡*2片"。
A13: 3 | B13: AI-Stack版本為何? GPU 資源管理 only or 需要 MLOps
B14: 客戶回答: GPU 資源管理 only
A15: 4 | B15: 客戶需要保固多久?
B16: 客戶回答:3年
A17: 5 | B17: 是否需要AI-Framework模版，若需要，需要幾個模版呢?
B18: 客戶回答:需要6個模版
A19: 6 | B19: 是否需要包含安裝
B20: 客戶回答:需要
A21: 7 | B21: 是否需要包含教育訓練
B22: 客戶回答:需要
A24: 需求確認
A25: 1 | B25: 客戶非教育單位，報價採商用版報價
A26: 2 | B26: V100顯示卡在AI-Stack原廠等級為Tier 1(參閱AI-Stack GPU Tier 對應表)，需求為2片
A27: 3 | B27: 版本為AI-Stack Express版
A28: 4 | B28: 需要三年保固
A29: 5 | B29: 需要AI-Framework模版*6個
A30: 6 | B30: 需要安裝
A31: 7 | B31: 需要教育訓練

Sheet SUMS各年限價值對照表
B2: 授權內含(非續約)SUMS各年限價值對照表
B3: 軟體授權價格區間 | C3: 首年 | D3: 第二年 | E3: 第三年 | F3: 第四年 | G3: 第五年
B4: 0~50萬 | C4: 2萬 | D4: 4萬 | E4: 6萬 | F4: 8萬 | G4: 10萬
B5: 50~150萬 | C5: 4萬 | D5: 8萬 | E5: 12萬 | F5: 16萬 | G5: 20萬
B6: 150~300萬 | C6: 6萬 | D6: 12萬 | E6: 18萬 | F6: 24萬 | G6: 30萬
B7: 300~800萬 | C7: 8萬 | D7: 16萬 | E7: 24萬 | F7: 32萬 | G7: 40萬
B8: 800~2000萬 | C8: 12萬 | D8: 24萬 | E8: 36萬 | F8: 48萬 | G8: 60萬
B9: 2000萬以上 | C9: 20萬 | D9: 40萬 | E9: 60萬 | F9: 80萬 | G9: 100萬
B12: Annual Value Reference Table of SUMS Included in the licenses(Not Renewal)
B13: Software License Price Range | C13: 1st Year | D13: 2nd Year | E13: 3rd Year | F13: 4th Year | G13: 5th Year
B14: 0–500,000 | C14: 20000 | D14: 40000 | E14: 60000 | F14: 80000 | G14: 100000
B15: 500,000–1,500,000 | C15: 40000 | D15: 80000 | E15: 120000 | F15: 160000 | G15: 200000
B16: 1,500,000–3,000,000 | C16: 60000 | D16: 120000 | E16: 180000 | F16: 240000 | G16: 300000
B17: 3,000,000–8,000,000 | C17: 80000 | D17: 160000 | E17: 240000 | F17: 320000 | G17: 400000
B18: 8,000,000–20,000,000 | C18: 120000 | D18: 240000 | E18: 360000 | F18: 480000 | G18: 600000
B19: Above 20,000,000 | C19: 200000 | D19: 400000 | E19: 600000 | F19: 800000 | G19: 1000000
